Workbook
Name _Hlk208463206: RajshreeM!$C$23
Name _Hlk209002039: RajshreeM!#REF!
Name HP4444explorations: 'HP4444'!$D$28:$E$33
Name HP4444TableNext: 'HP4444'!$D$17:$K$25
Name HP4444TableStarter: 'HP4444'!$D$6:$K$14
Name IM_015: "IM_015"
Name IM_053: "Picture 257"
Name IM_059: "Picture 258"
Name IM_065: "Picture 259"
Name IM_072: "Picture 260"
Name IM_087: "Picture 261"
Name IM_089: "Picture 262"
Name IM_099: "Picture 263"
Name IM_102: "Picture 264"
Name IM_104: "Picture 265"
Name IM_121: "Picture 266"
Name IM_136: "Picture 267"
Name IM_169: "Picture 268"
Name IM_171: "Picture 1"
Name IM_175: "Picture 269"
Name IM_176: "Picture 2"
Name IM_192: "Picture 270"
Name IM_193: "Picture 271"
Name IM_195: "Picture 273"
Name IM_197: "Picture 274"
Name IM_211: "Picture 275"
Name IM_216: "Picture 276"
Name IM_229: "Picture 277"
Name IM_230: "Picture 278"
Name IM_244: "Picture 279"
Name IM_336: "Picture 280"
Name IM_342: "Picture 281"
Name IM_343: "Picture 283"
Name IM_344: "Picture 284"
Name IM_387: "Picture 285"
Name IM_391: "Picture 286"
Name IM_403: "Picture 287"
Name IM342_jar: "Picture 5"
Name IndusScriptSet: mainData_collection!$A$2:$E$140
Name MD1531explorations: 'MD1531'!$D$28:$E$33
Name MD1531TableNext: 'MD1531'!$D$17:$K$25
Name MD1531TableStarter: 'MD1531'!$D$6:$K$14

Sheet mainData_collection
A2: வ எண் | B2: IM77 | C2: பட எழுத்து மதியாழகன் ivfont | D2: யஜனதேவம், கங்காளி, மதிவாணன், மதியழகன், பூரண சந்திரன், எனது ஆரம்ப நிலையில் என பலரின் எண்ணங்களின் வளரும் தொகுப்பு | E2: யஜனதேவம் வழியில் அகர வரிசை குறிப்பு
A3: 4 | B3: 1 | C3:  | D3: ஆயு மனிதன் ஆள் அவன் கடவுள் அய்யன், காவலாளி, கோ - தலைவன் | E3: அ
A4: 9 | B4: 4 | C4:  | D4: பாலா தண்டு இலை உரி தூக்கு தேன் கூடு கட்டு சோறு மடி பால் காம்பு கொடி தாண்டுதல் தம்பம் கம்பம் | E4: ந
A5: 22 | B5: 8 | C5:  | D5: ஆயு ஆள் வீரன் கத்தி வீரன் | E5: ஆ
A6: 117 | B6: 12 | D6: வட்டி ஆலமரம் தெய்வம் வேன் பலா மரம் பழம் | E6: வ
A7: 21 | B7: 15 | C7:  | D7: யவக்ஷ்ரிஷ்தி தானிய வியாபாரி நெய் எண்ணெய் வியாபாரி தூக்கு தூக்கி யாதவன் | E7: ய
A8: 51 | B8: 17 | D8: தடுலா வீரன் தண்டல்காரன் அரச வீரன் தலைவன் போராளி | E8: த
A9: 66 | B9: 38 | D9: யம யமா வியாபாரி பாணன் | E9: ய
A10: 39 | B10: 48 | C10:  | D10: சாக்காரா அணில் குறிஞ்சி உதயம் மொட்டு மலர் மகரந்தம் விந்து தாமரை பருத்தி | E10: ச
B11: 48 | C11: 
A12: 50 | B12: 51 | D12: மாத்தங்கா யானை தலை மதம் மதயானை முத்தம் தலை பிரட்டை | E12: ம
A13: 54 | B13: 52 | D13: சக்காரா அணில் ஓணான் பல்லி | E13: ச
A14: 44 | B14: 53 | C14:  | D14: ஹ ஸ பாக்கு வெட்டி கத்திரி குழந்தை நண்டு கொடுக்கு | E14: ஹ
A15: 122 | B15: 56 | C15:  | D15: அஸ்டபாத சிலந்தி நண்டு | E15: அஸ்
B16: 59 | C16:  | D16: ம, மீ, மீன், முனி , பேன், பெண் | E16: ம
A17: 27 | B17: 65 | C17:  | D17: அன்ங்க்க மீன் அம் மீன் அம்மான் அமர் தலைமை பூசாரி பேய் போயா போய் | E17: அம
A18: 16 | B18: 67 | C18:  | D18: மத்திய மீன் நீர் சிலந்தி புழு புலி பூசாரி போயா தலை பிரட்டை | E18: ம
A19: 86 | B19: 78 | D19: தர்த பறவை கருப்பு பறவை நீர் கோழி மரங்கொத்தி முசு பறவை | E19: த
A20: 119 | B20: 83 | D20: ஸயனே இராளி கழுகு இராஜாளி பறவை திமிங்கிலம் நீர் சிலந்தி | E20: ச
A21: 102 | B21: 84 | D21: யஸ்ட்டி குச்சி கை கால் தொடை மாமிசம் | E21: ய
A22: 2 | B22: 86 | C22:  | D22: அ அச் அச்சு அடி அசித் அசி ஜானி கோல் அடி கோல் | E22: அ
A23: 31 | B23: 87 | C23:  | D23: சோப்னா ஏணி இரு கோடுகள் ஈர்க்கு குச்சிகள் இரண்டு இணை | E23: ச
A24: 11 | B24: 89 | C24:  | D24: ஜரா நீர்வீழ்ச்சி நதி ஆறு ஜலம் நீர் மூன்று விபூதி பட்டை மூன்று உலகம் ஞாலம் அடுக்கு அலை வழி | E24: ஜ
A25: 14 | B25: 95 | C25:  | D25: சதுர் நான்கு வரிகள் கோடுகள் பாத்தி | E25: ச
A26: 41 | B26: 97 | C26:  | D26: அயுகா ஒன்று வரவு கால் அரை குறிப்பு கழிவு | E26: அ
A27: 96 | B27: 97 | C27:  | D27: ஏக்க ஒன்று அரை எண்ணம் | E27: ஏ
A28: 17 | B28: 99 | C28:  | D28: வி இரண்டு கொக்கி வகூத்தல் மீதி விகுதி தோர் தார் | E28: வ
A29: 28 | B29: 101 | C29:  | D29: நாளா கோரை கரும்பு இரண்டு ஈர் அரை ஒன்று ஓடை நீர் துளி மழை | E29: ந
A30: 93 | B30: 103 | C30:  | D30: த்தர மூன்று மூணு ஒழுகல் வடித்தல் | E30: த
A31: 108 | B31: 105 | C31:  | D31: சானா எடைக்கல் நான்கு நடவு நான்கு கால்வாய் | E31: ச
A32: 73 | B32: 107 | C32:  | D32: பஞ்சன் ஐந்து மரம் நீர் வீழ்ச்சி ஐ | E32: ப
A33: 65 | B33: 109 | C33:  | D33: ஸன் ஆறு எண் 6 மழை ஆறு நீர் | E33: ச
... A37: 84 | B37: 121 | C37:  | D37: சஞ்ஜான் மழை காற்று ஜலம் | E37: ஜ
A38: 35 | B38: 123 | D38: மன்த்த தீக்குச்சி வாள் கைப்பிடி வாள் 1 ½ 1 ¼ | E38: ம
A39: 7 | B39: 126 | C39:  | D39: தட்டுளா போராளி கலை முண்டா தடுமாற்றம் தாண்டு தடம் பாதை | E39: த
A40: 55 | B40: 127 | C40:  | D40: பஞ்சன் கை கரண்டி சுரண்டி கழி சுறடு | E40: ப
A41: 105 | B41: 129 | D41: காதனா அம்பு கொக்கி ஏர் கம்பி | E41: க
A42: 59 | B42: 130 | C42:  | D42: ஆஜினி கழி சுரட்டு கழி பாம்பு நாகம் உ ஊ ஒ ஓ ஔ | E42: அ
A43: 123 | B43: 130 | D43: ஓபசு கொண்டை முடி டப் ஆஃப் ஹேர் சுண்டு பாம்பு உ ஊ ஒ ஓ | E43: ஓ
A44: 114 | B44: 132 | D44: லதா கொடி வளைவு ஓட்டம் ஆறு நதி பாம்பு புழு கொடி பின்னல் கம்பி | E44: ல
A45: 111 | B45: 134 | D45: சிக்காரா மலை உச்சி சிகரம் குடில் குடிசை கூம்பு கூர் | E45: ச
A46: 43 | B46: 135 | C46:  | D46: சிகரா மலை உச்சி சிகரம் கூம்பு குடிசை | E46: ஸ
B47: 146 | C47: 
A48: 115 | B48: 147 | D48: சிக்காரா மயில் கொண்டை சித்திரம் இராட்டிணம் சூரியன் சக்கரம் மத்து சுழல் கூட்டம் | E48: ச
A49: 25 | B49: 149 | C49:  | D49: கிர்த்தம் தாயக்கட்டை கேடயம் சந்திப்பு போட்டி சண்டை | E49: க
A50: 112 | B50: 153 | D50: சிக்காரா மலை உச்சி சிகரம் குடில் குடிசை கூம்பு கூர் மலை பாதை வழி மேலே | E50: ச
A51: 113 | B51: 153 | D51: சிக்காரா மலை உச்சி சிகரம் அம்பு, போக்கு பாதை வழி மேலே | E51: ச
A52: 81 | B52: 155 | C52:  | D52: மந்தாரா மத்து மனிதன் குழந்தை சுழன்று விழும் விதை மரம் தள்ளு கனமான பொருளை | E52: ம
A53: 87 | B53: 155 | D53: மத்ய்ய மத்து குச்சி தழை பறந்து விழும் விதை தழை பறவை கொக்கு நாரை | E53: ம
A54: 90 | B54: 158 | D54: சிக்கா மயில் கொண்டை கிரீடம் குறியீடு இடம் அங்கு | E54: ச
A55: 46 | B55: 161 | D55: ரத்தர்வி பாம்பு கவை வீதி தெரு பிரிவு மரம் நதி இடி மின்னல் | E55: r
A56: 124 | B56: 167 | D56: ரதாதாரு Dalbergia மரம் செடி தண்டு மலர் கொத்து மருந்து மூலிகை | E56: ர
A57: 13 | B57: 169 | C57:  | D57: ரத்தர் பாம்பு அரிவாள் விரல் மரம் | E57: ர
A58: 30 | B58: 171 | C58:  | D58: தார்து தூக்கு மரம் தீ பந்தம் கை விரல் கீறி கிளரி மரம் கொடி கம்பம். | E58: த
A59: 80 | B59: 173 | C59:  | D59: தர்து மர கரண்டி கீறி விளக்கு தூக்கு மரம் கிளைகள் தார் மரம் உழுத நிலம் படல் | E59: த
A60: 76 | B60: 175 | C60:  | D60: சத்தர காளான் நாமம் பறந்து விழும் விதை மரம் முலை மலர் சுழலும் விதை | E60: ச
A61: 5 | B61: 176 | C61:  | D61: இஷிக புல்கட்டு ஈறு ஈ இ பல் காட்டு சீப்பு கீறி பயிர் நாற்று | E61: இ
A62: 69 | B62: 177 | C62:  | D62: இசீக்கா புல் கட்டு திண்பண்டம் கதிர் சுனை சோளம் திரி பின்னல். | E62: இ
A63: 82 | B63: 178 | D63: கிர்க்ஷ் ஏர் வகை படல் அடிக்கும் ஏர் | E63: க
A64: 60 | B64: 180 | D64: லதா பரவும் கொடி நீர் வீழ்ச்சி ஆறு தொங்கும் கயிறு ஆடை கொடி பூதம் | E64: ல
A65: 57 | B65: 182 | D65: மாயா குதிரை நாய் விலங்கு மண் குதிரை | E65: m
A66: 77 | B66: 182 | D66: ம்ர்க்ஷ் சீப்பு குதிரை அணை நீர் தாலி ஆரம் கீறி | E66: ம
A67: 101 | B67: 182 | D67: ம்ர்க்ஷா சீப்பு தாலி சரம் விலங்கு | E67: ம
A68: 47 | B68: 190 | C68:  | D68: யவா பார்லி பனை பயிர் நாற்று மரம் காடு படல் அரிசி வேலி | E68: ய
A69: 40 | B69: 192 | D69: மந்திரா குடியிருப்பு குடில் வீடு தொப்பி கொம்பு மந்திர் கோயில் மாடம் | E69: ம
B70: 193 | C70: 
A71: 64 | B71: 194 | C71:  | D71: பக்ஷ்த்ரா அடுப்பு மதகு விறகு அடுப்பு உலை | E71: ப
A72: 36 | B72: 197 | C72:  | D72: மிரிக்ஷா சீப்பு மாடி வீடு தூண் திட்டு மேடு | E72: ம
A73: 85 | B73: 202 | C73:  | D73: ம்ர்க்ஷ் சீப்பு வகை ஏணி மேடை சிக்கல் எடுக்கும் சீப்பு. | E73: ம
A74: 63 | B74: 204 | C74:  | D74: அக மாலை கூம்பு படி கோயில் | E74: அ
A75: 15 | B75: 205 | D75: அஜஷிரிங்கி ஆட்டு கொம்பு எம் தூதர் குத்து வாள் புலி நகம் | E75: அ
A76: 106 | B76: 206 | D76: மத்ய கிளப் சம்மட்டி இராட்டிணம் | E76: ம
A77: 23 | B77: 211 | C77:  | D77: நாலிக்கா அம்பு ஈட்டி முருகன் வேலன் நல்லான் காத்தவராயன் கோபுரம் குடில் | E77: ந
A78: 103 | B78: 212 | D78: தர்து கரண்டி தாமரை மலர் மனிதன் | E78: த
A79: 45 | B79: 214 | D79: தானக்கா காசு பணம் தாலி மேளம் தமுக்கு உடுக்கை | E79: த
A80: 75 | B80: 215 | D80: தானகா காசு வில்லைகள் கூம்பு மலை முட்டுகள் உடுக்கை | E80: த
A81: 24 | B81: 216 | C81:  | D81: அஷ்டபாசு எட்டுக் கால் சிலந்தி குழந்தை பாக்கு வெட்டி கத்திரி சிலந்தி தேள் கொடுக்கு நண்டு | E81: அஸ்
A82: 109 | B82: 219 | D82: அஸ்டபாதம் சிலந்தி சினை நண்டு குழந்தை தாய் | E82: அஸ்
A83: 56 | B83: 230 | C83:  | D83: தன்த பற்கள் மலை முகடுகள் வீடுகள் மரங்கள் கிராமம் | E83: த
A84: 67 | B84: 233 | D84: ஷிக்கா மயில் கொண்டை மலர் மலை வீடு மேடு கிராம வீடுகள் | E84: ச
A85: 20 | B85: 240 | D85: பக்ஷா பத்ரி வெற்றிலை பட்டி தொட்டி ஊர் இடம் சதுரம் சட்டம் வீடு பதக்கம்.. | E85: ப
A86: 92 | B86: 242 | D86: மந்திரா இருப்பிடம் வீடு மனை கால் அரை முக்கால் முழு கட்டம் | E86: ம
A87: 49 | B87: 244 | D87: தாடய மேளம் பாத்தி கிராமம் வீடுகள் கிணறு குளம் வரைவு | E87: த
A88: 37 | B88: 245 | C88:  | D88: நாள கோரைப்பாய் நிலம் பயிர் நிலம் பாத்தி சட்டம் சல்லடை பின்னல் துணி | E88: ந
A89: 99 | B89: 247 | D89: ரத் இரதம் பலகை பல்லாங்குழி கட்டு | E89: ர
A90: 38 | B90: 249 | C90:  | D90: வர்த்தி திரி விளக்கு உலக்கை சுத்தி வாய்க்கால் பாதை வழி கொடி கம்பம் | E90: வ
A91: 68 | B91: 253 | D91: உத்யாமா நூல் கண்டு குளம் உருளை வாய்க்கால் தொட்டி | E91: உ
A92: 58 | B92: 254 | C92:  | D92: மத்யா harrow கட்டு பிணைப்பு | E92: ம
A93: 125 | B93: 255 | D93: வாத்ர தறி நெய்தல் நீரோடை வடிகால் | E93: வ
A94: 71 | B94: 256 | C94:  | D94: கிர்த்தம் கோடாரி சுத்தி வீடு ஊர் கிணறு பீமன் | E94: க
A95: 18 | B95: 261 | C95:  | D95: இரதம் சதுரம் பாக்கு பள்ளம் கிணறு மோதிரம் | E95: ர
A96: 94 | B96: 264 | D96: உத்பான கிணறு அடுப்பு உலை கிராமம் உப்பளம் வயல் வடிகால் | E96: உ
A97: 12 | B97: 267 | C97:  | D97: ரதம் தேர் இரதம் கோதுமை அரிசி குடில் கோபுரம் தாயத்து கிணறு சதுரம் வைரம் முடுக்கு | E97: ர
A98: 26 | B98: 287 | C98:  | D98: அன்ங்க்க வளைவு பிறை நிலா கிண்ணம் புருவம் அடைப்பு கதவு குளம் விளரி | E98: அ
A99: 33 | B99: 294 | C99:  | D99: அன்ங்க்க வளைவு அணை இணை இரண்டு பாதை ஆறு ஓடை | E99: அ
A100: 32 | B100: 296 | C100:  | D100: அன்ங்க்க வளைவு படகு ஓடம் பொட்டு வில்லை முதுகு கிண்ணம் தட்டு | E100: அ
A101: 79 | B101: 299 | C101:  | D101: அன்க்க வளைவு பிறை வட்டி சட்டி குளம் அகம் | E101: அ
A102: 6 | B102: 301 | C102:  | D102: தன்வன் வில் வகை தனுஷ் கண் கரும்பு வில் தட்டு வட்டு கிண்ணம் சந்திரன் நிலவு பிறை போத்துக் கால் | E102: த
A103: 88 | B103: 302 | D103: தன்வன் வில் வகை வளரி குட்டை வாய்க்கால் | E103: த
A104: 89 | B104: 302 | D104: தன்வன் வில் வகை வளரி குட்டை வாய்க்கால் | E104: த
...

Sheet RajshreeM
A2: SNO | B2: IM | C2: Indus Symbol / Description | D2: Indus Symbol / Description | E2: Phonetic Value(s) | F2: Lexical Roots | G2: Meaning / Notes
A3: 52 | B3: 1 | D3: Human, worker, going/coming | E3: पु pu | F3: puruṣa = man | G3: Human figure, worker; meaning context-based
A4: 17 | B4: 8 | D4: Arc variation (overhand/neck) | E4: ग gā, गा gā | F4: gāna = sing; gala, gardan, gīva = neck | G4: Arc may vary in placement
A5: 8 | B5: 12 | D5: Carry on the shoulder | E5: का kā | F5: kavadi (carrier) | G5: —
A6: 73 | B6: 17 | D6: Shoot, brave, part, time | E6: वि vi | F6: vinda = shoot; vīra = brave; kāla = time; kala = part | G6: Growth, valor, temporality
A7: 58 | B7: 48 | D7: Straw, grain, reed, wages (sf:168) | E7: बी bī; बु bu; बू bū | F7: bīja = seed; būtā = sprout, decoration; balī = ear of paddy | G7: Also a number symbol (das, bis)
A8: 18 | B8: 53 | D8: Cow, place, city, tool to pick/rope (sf:130) | E8: ग ga, गो go | F8: gau = cow, bull; gahan = to take | G8: Cow, city/place, grasp
A9: 34 | B9: 59 | D9: Fish, water (381 sf) | E9: ण ṇa | F9: nadi = river; nayana = see | G9: In Prakrit, often n = ṇ; aquatic associations
A10: 33 | B10: 65 | D10: Shelter, cover, roof, noble (216) | E10: णि ṇi | F10: niche = below; ḍhakkaṇ = cover; ऋण (ṛṇa) = debt; aḍḍha (आढ्य) = wealthy, prosperous; āḍatī = broker | G10: Domestic, noble; sense of shelter/cover
A11: 59 | B11: 67 | D11: Fish with a horn or mustache (279) | E11: म ma | F11: machch = fish; muñchh = mustache | G11: Fish with distinctive features
A12: 35 | B12: 70 | D12: Stitch, egg, womb, inside (sf:73) | E12: णा ṇā | F12: nabhi = navel; pet = abdomen; ḍibbī = small box; aṇḍa = egg; andar, udara = inside, stomach; duti = navel; di (Karen) = egg | G12: Symbol of womb, egg, interior
A13: 7 | B13: 72 | D13: Cut, slice | E13: क ka | F13: kaṭṭa (half, raw, cut), meat | G13: —
A14: 27 | B14: 76 | D14: Bird | E14: चि ci | F14: chiḍi = bird | G14: —
... A19: 46 | B19: 96 | D19: Five, light beam | E19: प pa | F19: pañc = five | G19: Numerical; beam of light
A20: 4 | B20: 98 | C20: one | D20: One | E20: ए e | F20: ek (one) | G20: sf:177;
A21: 43 | B21: 99 | D21: Two (649) | E21: दि di; दु du | F21: div, dia, du = two | G21: —
A22: 39 | B22: 102 | D22: Three (sf:151) | E22: त ta, ति ti, ते tē | F22: t, te, tin = three | G22: Numeric marker
A23: 26 | B23: 104 | D23: Four | E23: च ca, चा cā | F23: chau, char = four | G23: —
A24: 28 | B24: 108
A25: 29 | B25: 109 | D25: Six | E25: छ cha | F25: chhah = six | G25: —
A26: 75 | B26: 112 | D26: Seven | E26: सा sā | F26: sāt = seven | G26: Numerical symbol
A27: 12 | B27: 124 | D27: Broken, part (sf:78) | E27: ख kha | F27: khaṇḍi, tuṭi = small, broken | G27: —
A28: 69 | B28: 127 | D28: Hanging | E28: ल la | F28: laṭak = hang | G28: Symbol of suspension
A29: 70 | B29: 129 | D29: Rolling, slope, up/down/behind | E29: लु lu | F29: luḍaknā = roll | G29: Motion, slope
A30: 30 | B30: 130 | E30: झ jha | F30: —dhāra (root); “to pour, to mold” | G30: Used in the sense of shaping vessels, toys from molten material
A31: 76 | B31: 134 | D31: Apex, top, sharp | E31: सि si; सी sī; | F31: śirṣa (head, top), śikhā (crest, peak, tuft). | G31: Often functions purely as the sound-value si, irrespective of semantic sense.
A32: 11 | B32: 135 | D32: Angle/corner | E32: को ko | F32: kona (angle), naka (cross over) | G32: —
A33: 37 | B33: 135 | D33: Corner | E33: णु ṇu | F33: nukkad = corner | G33: —
A34: 36 | B34: 137 | D34: Stop, fight (23) | E34: णा ṇā; रु ru; रू rū | F34: na = no; ruka = stop; ḍaṅgal = fight, meet | G34: Associated with prohibition, conflict, and encounter
A35: 62 | B35: 149 | D35: Journey, meet, cross (sf:92) | E35: या yā; मा mā | F35: yātra = journey; mārga = road | G35: Movement, travel, crossing
A36: 60 | B36: 150 | D36: Meet, travel (63) | E36: मि mi | F36: milan = meeting; mārga = road; caukka = crossing, courtyard | G36: Junction where roads meet
A37: 9 | B37: 155 | D37: Underarm, class | E37: का kā | F37: kankh (under arm, class) | G37: 73
A38: 32 | B38: 162 | D38: Stump, tree; fear, respect? | E38: त ठु ṭhu | F38: —taru: tree, tana, thunth: stump | G38: —
A39: 38 | B39: 162 | D39: Stump, tree; respect, fear (212) | E39: त ta; ठु ṭhu | F39: taru = tree; tunta = trunk | G39: Also linked with respect, fear, tremble, surrender
A40: 2 | B40: 169 | D40: Reed | E40: इ i, ई ī | F40: ikhu (reed) | G40: sf:232
A41: 80 | B41: 171 | D41: Wages, hand, giving (132) | E41: ह ha; हा hā | F41: hath = hand; sulā, dol, dīhāḍī = wages; dā = give, take; bahu (compound) | G41: Payment, hand, giving
A42: 14 | B42: 180
A43: 81 | B43: 180 | D43: Scrape, loosen, find, search | E43: ह ha | F43: hakai, khudāi = scrape, dig | G43: Searching, loosening
A44: 15 | B44: 181 | D44: Collect, fingers, scrape; pincer/claw tool | E44: खु khu (sign 181 clue) | F44: khurucana = scrape; khodana = dig; surra, suta = thread | G44: What do you do with a pincer or claw?
A45: 21 | B45: 192
A46: 22 | B46: 193 | D46: Divide into two parts? | E46: घा ghā bha | F46: bhaga, bha = divide | G46: —also rays, shine
A47: 51 | B47: 197 | D47: Prominent, elevated, temple (60) | E47: पि pi, पी pī | F47: pīṭh = seat, high, east; matha = monastery; maṇḍir = temple; mahal = palace | G47: Convex, rising, elevated
A48: 61 | B48: 205 | D48: Tooth, pointed, tusk | E48: मे me | F48: mellu = molar, tusk; PIE malla = strong one who breaks teeth | G48: Symbol of tusk/strength
A49: 41 | B49: 211 | D49: Arrow | E49: ति ti; ती tī | F49: tir = arrow; ban = bow; isu = arrow | G49: Weapon imagery
A50: 74 | B50: 216 | D50: Bull, pincers, rope (90) | E50: स sa | F50: śastra = weapon; sandāsī = pincers; chi/śimta = tongs, forceps; khīcana = to pull | G50: Male animals (bull, goat, sheep); pulling tools
A51: 67 | B51: 225 | D51: rope tied to an animal’s nose | E51: रा rā | F51: ras = rope | G51: Suggests tethering, harness
A52: 20 | B52: 230 | C52: , | D52: Teeth of a saw; valley fringe; festival | E52: घा ghā, दा dā | F52: danta = teeth; ghaṭi, ghaṭ = valley fringe; li = Aravalli range | G52: Festival association?
A53: 40 | B53: 233 | D53: Star, flower, beauty (sf:29) | E53: ता tā | F53: tara = star; ratri = night; phirna = reel; khil = bloom; sundar, śubh = beauty | G53: “Three triangles”; connected to stars, flowers, auspiciousness
A54: 66 | B54: 233 | D54: Star, flower, beauty (sf:29, three-triangle) | E54: रा rā; ता tā | F54: tārā = star; rātri = night; phirna = reel; khil = bloom; sundar, śubh = beauty | G54: Celestial, floral, auspicious markers
A55: 57 | B55: 244 | D55: Fence (sf:89) | E55: बा bā; br, vr | F55: bāṛa, baṛa = dwelling, doors, fence, elder | G55: Boundary marker; enclosure; elderhood
A56: 13 | B56: 245 | D56: Parcel, farm (206) | E56: खे khe | F56: khet = farm; kheda = village; kho kha = parcel, farm | G56: —
A57: 45 | B57: 249 | D57: Stool (170) | E57: प pa | F57: pāṭ = stool; panna = measurement unit; bat = measure | G57: Stool, lease, measurement
A58: 19 | B58: 252 | D58: Cube, hammer | E58: घ gha | F58: ghan = hammer, cloud, dark | G58: —
A59: 10 | B59: 254 | D59: Chair, bed, throne | E59: कु ku, कू kū | F59: kursi (chair) | G59: 35; also angle, corner, breast?
A60: 42 | B60: 258 | D60: Pole, wall | E60: थ tha | F60: thambā = pole; iṇṭ = brick | G60: Architectural/post sign
A61: 23 | B61: 261 | D61: Encircle, rotate | E61: घे ghe | F61: gher = encircle; ghum = rotate | G61: —
A62: 47 | B62: 261 | D62: Town, complete | E62: प pa | F62: pur = town; pūrṇa = complete | G62: Settlement, wholeness
A63: 48 | B63: 267 | D63: Deposit, head, authority, big house (376) | E63: प pa | F63: — | G63: Interpreted as a logogram; values include pāv, peḍhī, pāl, pakkha, pari, paḍi
A64: 49 | B64: 267 | D64: Deposit, head, responsibility, authority, big house (sf:376) | E64: पाव pāv; पेढी peḍhī; पाल pāl; पक्ख pakkha; परि pari; पडि paḍi; पडिभू paḍibhū | F64: pāv = quarter, share; pāla = guardian, protector; pakkha = fortnight, side, party; peḍhī = bank, office, firm; pari = around, surrounding; paḍi / pratibhū = guarantor, surety | G64: A logogram representing civic/administrative authority and responsibility. Values extend across economic (peḍhī), temporal (pakkha), protective (pāla), relational (pari), and legal (paḍi / pratibhū) domains. The semantic field spans obligation, surety, civic institutions, and calendrical reckoning.
A65: 77 | B65: 293 | D65: Crown, head, sun, new moon, month, horizon, white/silver (136) | E65: सि si; सी sī; सिअ sia | F65: śiśa = head, crown; sia (śukla) = white, bright; rājā, pati, pitā = king, lord, father | G65: Crown/throne; sovereignty; divine brightness; lunar/solar cycle
A66: 31 | B66: 307 | E66: ट ṭa, टा ṭā, टि ṭi, टी ṭī, टु ṭu | F66: — | G66: —Possibly shares many features with ट-वर्ग (ṭa-group). Assumed links: ghaṇṭā = hour, ḍaṅka = drum sound, dhanuṣ = bow
A67: 3 | B67: 328 | D67: Mortar | E67: उ u, ऊ ū | F67: ukhā, ukhālī (mortar) | G67: —
A68: 78 | B68: 336 | D68: Hear, needle, sew (236) | E68: सु su | F68: sūī, śuci = needle; suā = ritual implement for ghee | G68: Sewing, ritual pouring tool
A69: 50 | B69: 341 | D69: Human feet | E69: पा pā, पे pe | F69: pair, pāv = foot | G69: Feet, walking
A70: 1 | B70: 342 | D70: Jar | E70: अ a, आ ā | F70: agar (place, warehouse) | G70: Often at end of name; sa, da = respected, male Jar with gun sign (rekha), logogram
A71: 5 | B71: 343 | E71: ag, ae | F71: agar, agrim (elder, head) | G71: head, chief, collector; also →
A72: 6 | B72: 344 | D72: Adi / Adra | E72: — | F72: adra (wet), ādi (many), ida | G72: a + di → beginning, multiplicity
A73: 79 | B73: 365 | D73: Insert? | E73: सु su | F73: — | G73: Possible insertion/placement sign
A74: 55 | B74: 367 | D74: Flower / lotus | E74: फु phu | F74: phul = flower; padma = lotus; padma = number | G74: Flower, lotus, numerical use
A75: 71 | B75: 373 | D75: Round, head (sf:61) | E75: व va | F75: golā = round; vrata = circle | G75: Circular form, roundness
A76: 53 | B76: 375 | D76: Fruit | E76: फ pha | F76: phala = fruit; bīja = seed | G76: Fruit and seed
A77: 56 | B77: 379 | D77: Pod, seed | E77: — | F77: phālī = pod; bīja = seed | G77: Pod, seed
A78: 72 | B78: 391 | D78: Circle with hatching/division (abstract) | E78: vai, vatta | F78: vai (marker) | G78: Division, segmented circle, year, time, area
A79: 54 | B79: 400 | D79: Flower, bud, bead | E79: फू phū | F79: phūl = flower | G79: Flower, bead, bud
A80: 68 | B80: 402 | D80: Writing instrument, quill, fin, awe, fear (99) | E80: रु ru; रू rū | F80: ruā = hair; rekh, lipi, likh = write, script; Karen ru = to write/scratch lines | G80: rajjū = rope; rajjū-sabhā = writer’s guild, toll-house
A81: 63 | B81: 403 | D81: Joined with a gun sign | E81: यु yu; जु ju | F81: yukta = joined; yugam = pair, twin | G81: Conjoined, twin, yoke
A82: 65 | B82: 415 | D82: Rope or chain | E82: र ra | F82: rajju = rope; raśi, saṅkal, laḍī = chain | G82: Binding, tether

Sheet dataStructured_Kangali_Puru
B3: KangaliRef | C3: Seal_Ref | D3: PositionFR | E3: IM_Ref_Pic/Ivfont/Kangali | F3: IM_Ref_No_RightToLeft | G3: Kangali | H3: Puru
B4: P99/SN194/103 | C4: MD1531 | D4: 0 | F4: =_xlfn.TEXTJOIN(";",TRUE,F5:F8) -> 171;59;342;176 | G4: சீறி பேன் > முக்கியா; கி நிசானி > தெரிகிறது, இருக்கிறது, உண்மை | H4: கை உயர்த்தி பேசு பால் வளம் முனிகள் பராமரிப்பில் வந்தது
C5: MD1532 | D5: 1 | E5: =VLOOKUP(F5,mainData_collection!$B$2:$D$180,2) ->  | F5: 171 | G5: சீறி | H5: கை,ஐந்து, உயர்த்து, தீ பந்தம் , கொடி
C6: MD1532 | D6: 2 | E6: =VLOOKUP(F6,mainData_collection!$B$2:$D$180,2) ->  | F6: 59 | G6: பெண், பேன் | H6: மீன், முனி, நீர் சிலந்தி,போர்த்திய ஆள் பெண், புழு, புலி
C7: MD1532 | D7: 3 | E7: =VLOOKUP(F7,mainData_collection!$B$2:$D$180,2) ->  | F7: 342 | G7: ஆனா | H7: மாடு, பசு, ஆ, அண்டா , குளம், மரக்கால் , சால்
C8: MD1532 | D8: 4 | E8: =VLOOKUP(F8,mainData_collection!$B$2:$D$180,2) ->  | F8: 176 | G8: கீரா | H8: ஐந்து, விரல்கள், கீறி,சீப்பு, அரிவாள்
B9: P64/Sn4/HR1940-581 | C9: HP4444 | D9: 0 | F9: =_xlfn.TEXTJOIN(";",TRUE,F10:F13) -> 119;87;342;176 | G9: பாணி ரக்கானெக் > நீர் வைக்கபடுகிறது ; கி நிசானி > தெரிகிறது, இருக்கிறது, உண்மை | H9: இரட்டை மாட்டு ஏர் உழுது விவசாயம் அருமை
C10: HP4444 | D10: 1 | E10: =VLOOKUP(F10,mainData_collection!$B$2:$D$180,2) ->  | F10: 119 | G10: யேர் | H10: நீர், ஏர், உழவு, மழை, பன்னிரண்டு, எண்ணிக்கை, அடுக்கு
C11: HP4444 | D11: 2 | E11: =VLOOKUP(F11,mainData_collection!$B$2:$D$180,2) ->  | F11: 87 | G11: இரு | H11: இரண்டு, ஈர்,
C12: HP4444 | D12: 3 | E12: =VLOOKUP(F12,mainData_collection!$B$2:$D$180,2) ->  | F12: 342 | G12: ஆனா | H12: மாடு, பசு, ஆ, அண்டா , குளம், மரக்கால் , சால்
C13: HP4444 | D13: 1 | E13: =VLOOKUP(F13,mainData_collection!$B$2:$D$180,2) ->  | F13: 176 | G13: கீரா | H13: ஐந்து, விரல்கள், கீறி,சீப்பு, அரிவாள்
B14: P62/Sn8/HR1940-372 | C14: HP4372 | D14: 0 | F14: =_xlfn.TEXTJOIN(";",TRUE,F15:F18) -> 48;136;193;342 | G14: பருத்தி பயிர், ஆடை நெய்து தயார் நிலையை காட்டுகிறது – இது வியாபாரி தம்மிடம் இருப்பதை தெரிவிக்கிறது | H14: செல்வம் நிறைந்த பகுதி என்றும் காடு மலை சார்ந்த பகுதி என்ற குறிப்பு
C15: HP4372 | D15: 1 | E15: =VLOOKUP(F15,mainData_collection!$B$2:$D$180,2) ->  | F15: 48 | G15: பருத்தி | H15: மலை தேன், மலர்,
C16: HP4372 | D16: 2 | E16: =VLOOKUP(F16,mainData_collection!$B$2:$D$180,2) ->  | F16: 136 | G16: கோபுரம் குவியல் அம்பாரம் | H16: குடிசை, வீடு, கோபுரம், குவியல்
C17: HP4372 | D17: 3 | F17: 193 | G17: துணி ஆடை | H17: தொப்பி,
C18: HP4372 | D18: 4 | E18: =VLOOKUP(F18,mainData_collection!$B$2:$D$180,2) ->  | F18: 342 | G18: ஆனா | H18: மாடு, பசு, ஆ, அண்டா , குளம், மரக்கால் , சால்
C19: HP4372 | D19: 5 | E19: =VLOOKUP(F19,mainData_collection!$B$2:$D$180,2) ->  | F19: 176 | G19: கீரா | H19: ஐந்து, விரல்கள், கீறி,சீப்பு, அரிவாள்
C20: HP4372 | D20: 6 | E20: =VLOOKUP(F20,mainData_collection!$B$2:$D$180,2) ->  | F20: 176 | G20: கீரா | H20: ஐந்து, விரல்கள், கீறி,சீப்பு, அரிவாள்
B21: P100/SN200/1536 | C21: MD1536 | D21: 0 | F21: =_xlfn.TEXTJOIN(";",TRUE,F22:F28) -> 146;195;343;403;87;342;1 | G21: காற்று ஓடை ஆதி சக்தி மாதா முக்கியம் | H21: காற்று மத்து கடைய, மழைநீர் கால்வாயில் ஓட, நீர் குளம் குட்டை ஏரியில் நிரம்ப, அக்கமார்கள் நடந்து, நீர் குடம் எடுக்க, என்னே அந்நாள், கடவுள் கருணை
C22: MD1536 | D22: 1 | F22: 146 | G22: மாட்டாயா | H22: காற்று மத்து
C23: MD1536 | D23: 2 | E23: =VLOOKUP(F23,mainData_collection!$B$2:$D$180,2) ->  | F23: 195 | G23: கால்வாள் | H23: ஓடை , வாய்க்கால்
C24: MD1536 | D24: 3 | F24: 343 | G24: ஆந்தி | H24: குளம், குட்டை
C25: MD1536 | D25: 4 | F25: 403 | G25: அக்கா | H25: அக்கா , வளையல்
C26: MD1536 | D26: 5 | E26: =VLOOKUP(F26,mainData_collection!$B$2:$D$180,2) ->  | F26: 87 | G26: இரு | H26: இரு, நடந்து, இரண்டு
C27: MD1536 | D27: 6 | F27: 342 | G27: ஆனா | H27: நீர் குடம்
C28: MD1536 | D28: 7 | E28: =VLOOKUP(F28,mainData_collection!$B$2:$D$180,2) ->  | F28: 1 | G28: ஆள் | H28: கடவுள், அந்நாள்
B29: P97/Sn187/1420 | C29: MD1420 | D29: 0 | F29: =_xlfn.TEXTJOIN(";",TRUE,F30:F36) -> 175;230;344;53;65;233;342 | G29: வேலச்சியாளின் புத்திரன் பகந்தி போது கோயா தலை முக்கிய கோருமேடு | H29: மூன்று உறி விளக்கு எண்ணெய் ஆதான் கோரு மேட்டு மலை தலை முண்டாசும் போத்து கோயா பகந்தியும் பகிர்ந்து கொண்டார்கள்
C30: MD1420 | D30: 1 | E30: =VLOOKUP(F30,mainData_collection!$B$2:$D$180,2) ->  | F30: 175 | G30: வேலச்சியாள் | H30: ஆமணக்கு விதை, உறி, வேலு ஆச்சியாள்
C31: MD1420 | D31: 2 | E31: =VLOOKUP(F31,mainData_collection!$B$2:$D$180,2) ->  | F31: 230 | G31: முறி | H31: முறி, உடைத்தால், எடுத்தல் , அரைத்தல், மூவர்
C32: MD1420 | D32: 3 | E32: =VLOOKUP(F32,mainData_collection!$B$2:$D$180,2) ->  | F32: 344 | G32: பகந்தி | H32: பகந்தி முனிவர், விஷ்ணு, நாமம்
C33: MD1420 | D33: 4 | E33: =VLOOKUP(F33,mainData_collection!$B$2:$D$180,2) ->  | F33: 53 | G33: போத்து கோயா | H33: போத்து கோயா கரும்பு விளைச்சல் சமுதாயம்
C34: MD1420 | D34: 5 | E34: =VLOOKUP(F34,mainData_collection!$B$2:$D$180,2) ->  | F34: 65 | G34: தலை முக்கியா | H34: தலைவர், முக்கியஸ்தர் , தலை கட்டு
C35: MD1420 | D35: 6 | E35: =VLOOKUP(F35,mainData_collection!$B$2:$D$180,2) -> 0 | F35: 233 | G35: கோரு மேட்டா | H35: மலை கிராமங்கள் , வீடுகள், கூட்டம்
D36: 7 | E36: =VLOOKUP(F36,mainData_collection!$B$2:$D$180,2) ->  | F36: 342 | G36: ஆந்த | H36: அளவீடு, மரக்கால், மாடுகள் , வழக்கம், முறை
B37: P86/SN134/2587 | C37: MD2587 | D37: 0 | F37: =_xlfn.TEXTJOIN(";",TRUE,F38:F40) -> 86;102;15 | G37: இவர் முதன்மை பாதுகாவலர் | H37: வரும் முந் காப்போன் காவடியோன் முருகன் / மகமாயி மும்மாரி முத்துமாரி
D38: 1 | E38: =VLOOKUP(F38,mainData_collection!$B$2:$D$180,2) ->  | F38: 86 | G38: ஒரு | H38: ஒன்று, கோல், காவல், மழை
D39: 2 | E39: =VLOOKUP(F39,mainData_collection!$B$2:$D$180,2) ->  | F39: 102 | G39: மூன் | H39: மூன்று, முப்போகம், மும்மாரி
D40: 3 | E40: =VLOOKUP(F40,mainData_collection!$B$2:$D$180,2) ->  | F40: 15 | G40: காவடியாள் ஆந்த | H40: காவடி, பால் காரர், தீவனம் அளிப்பவர் , மாட்டு பட்டி காவலர்
B41: P76/SN82/2110 | C41: MD2507 | D41: 0 | F41: =_xlfn.TEXTJOIN(";",TRUE,F42:F47) -> 375;65;72;336;89;211 | G41: விளைநிலம் முக்கியம், தலை முக்கியம், சேரா பொய்யா தேவன் முக்கியம் என்பர் நூலார் | H41: நெல் பாதுகாப்பு அன்னம் பாதுகாப்பு, தலையாய சேரா ஆய - நூறு மூவாயிரம் நூலோர் பாதுகாப்பு
D42: 1 | E42: =VLOOKUP(F42,mainData_collection!$B$2:$D$180,2) -> 0 | F42: 375 | G42: நெல் பாது | H42: நெல் விதை
D43: 2 | E43: =VLOOKUP(F43,mainData_collection!$B$2:$D$180,2) ->  | F43: 65 | G43: தலாபோய் | H43: தலை முன் நிற்பவர்
D44: 3 | E44: =VLOOKUP(F44,mainData_collection!$B$2:$D$180,2) ->  | F44: 72 | G44: சேராபோய் | H44: சேரன் முன் நிற்பவர்
D45: 4 | E45: =VLOOKUP(F45,mainData_collection!$B$2:$D$180,2) -> 0 | F45: 336 | G45: நுர் | H45: நூர் , நூறாயிரம் , நெல் அரைத்தல்
D46: 5 | E46: =VLOOKUP(F46,mainData_collection!$B$2:$D$180,2) ->  | F46: 89 | G46: மூன் | H46: மூவாயிரம்
D47: 6 | E47: =VLOOKUP(F47,mainData_collection!$B$2:$D$180,2) ->  | F47: 211 | G47: நூல், ஆர் | H47: உறுதி பயன் நூலோர் , நிலை நிறுத்து
B48: P61/SN3/MD1937-420 | C48: MD2420 | D48: 0 | F48: =_xlfn.TEXTJOIN(";",TRUE,F49:F54) -> 3;216;229;343;59;342 | G48: இங்கு கோயா பாரி பகந்தி குரு முக்கியா உள்ளார் | H48: அகோரி பகந்தி முத்தன்
D49: 1 | E49: =VLOOKUP(F49,mainData_collection!$B$2:$D$180,2) ->  | F49: 3 | G49: ஆள் | H49: ஆள்
D50: 2 | E50: =VLOOKUP(F50,mainData_collection!$B$2:$D$180,2) ->  | F50: 216 | G50: கோயா | H50: கோயா சின்னம்
D51: 3 | E51: =VLOOKUP(F51,mainData_collection!$B$2:$D$180,2) -> 0 | F51: 229 | G51: பாரி | H51: பாரி சின்னம்
D52: 4 | E52: =VLOOKUP(F52,mainData_collection!$B$2:$D$180,2) ->  | F52: 343 | G52: பகந்தி | H52: பகந்தி முனிவர், விஷ்ணு, நாமம்
D53: 5 | E53: =VLOOKUP(F53,mainData_collection!$B$2:$D$180,2) ->  | F53: 59 | G53: முட்டவா போய | H53: முனிவர், முதலாம் குரு
D54: 6 | E54: =VLOOKUP(F54,mainData_collection!$B$2:$D$180,2) ->  | F54: 342 | G54: ஆந்த | H54: ஆம், அம், ஆ , அண்டா, குண்டா, மரக்கால், அளவு, மாடு, பசு
B55: P60/SN1/MD1937-49 | C55: WA9811 | D55: 0 | F55: =_xlfn.TEXTJOIN(";",TRUE,F56:F60) -> 29;336;99;104;162 | G55: இர்பில் அம்பாள் நுர்தோர் நாலோமால் [ இருவில் அம்பாள் கிராமத்தில் நல்ல புகழ் பெற்றவர்] | H55: இருவில் பெஉத்தி ருமாள் நூற்றில் ஒரு நல்ல பெருமாள் / இரட்டை மாட்டு செக்கு நல்லதோர் உத்தி
D56: 1 | E56: =VLOOKUP(F56,mainData_collection!$B$2:$D$180,2) -> 0 | F56: 29 | G56: இர்பில் அம்பாள் | H56: இரட்டை மாடு பூட்டிய
D57: 2 | E57: =VLOOKUP(F57,mainData_collection!$B$2:$D$180,2) -> 0 | F57: 336 | G57: நூர் | H57: செக்கு நூர் நொறுக்கு
D58: 3 | E58: =VLOOKUP(F58,mainData_collection!$B$2:$D$180,2) ->  | F58: 99 | G58: தோர் | H58: வோர்
D59: 4 | E59: =VLOOKUP(F59,mainData_collection!$B$2:$D$180,2) ->  | F59: 104 | G59: நால் | H59: நல்ல
D60: 5 | E60: =VLOOKUP(F60,mainData_collection!$B$2:$D$180,2) -> 0 | F60: 162 | G60: ஓமால் | H60: மகசூல், நெல், ஈட்டியது
B61: P60/SN2/MD1937-524 | C61: MD2015 | D61: 0 | F61: =_xlfn.TEXTJOIN(";",TRUE,F62:F64) -> 336;89;211 | G61: கிராம முக்கியா / முதன்மை அதிகாரி | H61: மூன்று கானம் நிறுத்து ஒரு பணம் / ஒரு செக்கு கானம் நிறுத்து மூன்று பணம் / கானம் மூன்று நிறுத்து ஒரு பாலன் எடை
D62: 1 | E62: =VLOOKUP(F62,mainData_collection!$B$2:$D$180,2) -> 0 | F62: 336 | G62: நூர் | H62: செக்கு, நொறுக்கு, சட்டியும் அகப்பையும், செக்கு கானம்
D63: 2 | E63: =VLOOKUP(F63,mainData_collection!$B$2:$D$180,2) ->  | F63: 89 | G63: மூன் | H63: மூன்று, வேலி
D64: 3 | E64: =VLOOKUP(F64,mainData_collection!$B$2:$D$180,2) ->  | F64: 211 | G64: சார்,ஆர் | H64: அம்பு, ஈட்டி, காவல், வேலன், முருகன், துலா முள்
B65: P61/SN5/MD1937-669 | C65: MD2669 | D65: 0 | F65: =_xlfn.TEXTJOIN(";",TRUE,F66:F68) -> 59;121;342 | G65: குரு முக்கியாவின் கருணை | H65: முனிகளால் பால் வளம் மிகுதி
D66: 1 | E66: =VLOOKUP(F66,mainData_collection!$B$2:$D$180,2) ->  | F66: 59 | G66: முட்டவா போய | H66: முனி
D67: 2 | E67: =VLOOKUP(F67,mainData_collection!$B$2:$D$180,2) ->  | F67: 121 | G67: பீர | H67: பீரிட, மிக, முழுமையான
D68: 3 | E68: =VLOOKUP(F68,mainData_collection!$B$2:$D$180,2) ->  | F68: 342 | G68: ஆந்த | H68: பால், பசு, மரக்கால்
B69: P61/SN6/HR1940-344 | C69: HP4344 | D69: 0 | F69: =_xlfn.TEXTJOIN(";",TRUE,F70:F75) -> 177;197;192;341;89;328 | G69: இந்த மூன்றும் அம்பாரத்தில் சபையில் நமது வளர்ச்சிக்கான அளவீடுகளாக வைக்க வேண்டும்: தங்கம், ஆடை, வீடு இவற்றின் நுட்பம் | H69: நம்முடைய புஷ்டி தாது சக்தியின் அளவீடு நம்மிடம் உள்ள மதிய மாளிகைகள், ஆடை ஆபரணம், தங்கம் உலோகம் என்ற மூன்று துறையின் வளர்ச்சி
D70: 1 | E70: =VLOOKUP(F70,mainData_collection!$B$2:$D$180,2) ->  | F70: 177 | G70: கோலா | H70: அளவு கோல்
D71: 2 | E71: =VLOOKUP(F71,mainData_collection!$B$2:$D$180,2) ->  | F71: 197 | G71: மாடா | H71: மாட மாளிகை வீடு
D72: 3 | E72: =VLOOKUP(F72,mainData_collection!$B$2:$D$180,2) -> 0 | F72: 192 | G72: குடரதே | H72: ஆடை ஆபரணம்
D73: 4 | E73: =VLOOKUP(F73,mainData_collection!$B$2:$D$180,2) -> 0 | F73: 341 | G73: கோவதா | H73: தங்கம், உலோக தொழில்
D74: 5 | E74: =VLOOKUP(F74,mainData_collection!$B$2:$D$180,2) ->  | F74: 89 | G74: மூந்த | H74: மூன்றும்
D75: 6 | E75: =VLOOKUP(F75,mainData_collection!$B$2:$D$180,2) ->  | F75: 328 | G75: ஆளாங்க | H75: அளவு
B76: P62/SN12/MD1937-449 | C76: MD1561 | D76: 0 | F76: =_xlfn.TEXTJOIN(";",TRUE,F77:F79) -> 204;230;342 | G76: தானிய குவியல் உள்ளது | H76: தானிய குவியல்கள் மூட்டைகள் மாட்டு வண்டியில் அனுப்ப தயாராக உள்ளது
D77: 1 | E77: =VLOOKUP(F77,mainData_collection!$B$2:$D$180,2) ->  | F77: 204 | G77: தூக்கா தூக்கல் குவியல் | H77: குவியல், கோபுரம்
D78: 2 | E78: =VLOOKUP(F78,mainData_collection!$B$2:$D$180,2) ->  | F78: 230 | G78: முறி மூன்று உறி தொகுப்பு | H78: மூட்டைகள் உறி நிறைய மூன்று நிறை
D79: 3 | E79: =VLOOKUP(F79,mainData_collection!$B$2:$D$180,2) ->  | F79: 342 | G79: ஆந்த அவை | H79: மாடு, பசு, ஆம், அம் , ஆ , ஆந்தை
B80: P62/SN14/MD1940-502 | C80: MD1550 | F80: =_xlfn.TEXTJOIN(";",TRUE,F81:F83) -> 67;244;342 | G80: சபையில் முக்கிய பிரதான் தலைமை வகிக்கிறார் | H80: கோயில் முனிவர் மக்களுக்கு பாதுகாப்பு / முனி ஈஸ்வரர் கோயில் / முனி எசவரர் கோயிலுக்கு அளித்த பசு மாடு
E81: =VLOOKUP(F81,mainData_collection!$B$2:$D$180,2) ->  | F81: 67 | G81: அதி முக்கிய முனி ஈஸ்வர் | H81: அதி முக்கிய முனி ஈஸ்வர்
E82: =VLOOKUP(F82,mainData_collection!$B$2:$D$180,2) -> 0 | F82: 244 | G82: சபை கோயில் | H82: சபை கோயில்
E83: =VLOOKUP(F83,mainData_collection!$B$2:$D$180,2) ->  | F83: 342 | G83: உள்ளார், காட்சி அளிக்கிறார் | H83: உள்ளார், காட்சி அளிக்கிறார்
B84: P62/SN16/- | C84: 974 | F84: =_xlfn.TEXTJOIN(";",TRUE,F85:F86) -> 244;342 | G84: சபை கூட்டம் செல்கிறது | H84: கோயிலுக்கு நேர்ந்த மாடு , மாட்டு பட்டி, ஆயிரம் மாடு
F85: 244 | G85: கோயில் | H85: கோயில், கட்டிடம்
F86: 342 | G86: ஆந்த | H86: மாடு பசு
B87: P75/SN76/MD-3023 | C87: MD3023 | D87: 0 | F87: =_xlfn.TEXTJOIN(";",TRUE,F88:F95) -> 183;169;99;387;59;182;293;342 | G87: பத்தோமாள் விளைநிலம் முக்கியம் அத்துடன் பத்து போத்து கால் முக்கியம் | H87: சேராமான் முனியிடம் பத்து பட்டி ஓமாளிகை பத்து நெல் போது பத்து போத்துகால் கரும்பு பயிர் இடப்பட்டுள்ளது
D88: 1 | E88: =VLOOKUP(F88,mainData_collection!$B$2:$D$180,2) -> 0 | F88: 183 | G88: பகீ | H88: பத்து
D89: 2 | E89: =VLOOKUP(F89,mainData_collection!$B$2:$D$180,2) ->  | F89: 169 | G89: ஓமாள் | H89: ஓமாளிகை
D90: 3 | E90: =VLOOKUP(F90,mainData_collection!$B$2:$D$180,2) ->  | F90: 99 | G90: தோர் | H90: அத்துடன்
D91: 4 | E91: =VLOOKUP(F91,mainData_collection!$B$2:$D$180,2) ->  | F91: 387 | G91: நெல் பாது | H91: நெல் போது விதை
D92: 5 | E92: =VLOOKUP(F92,mainData_collection!$B$2:$D$180,2) ->  | F92: 59 | G92: சேரா போய | H92: சேராமான் முனி
D93: 6 | E93: =VLOOKUP(F93,mainData_collection!$B$2:$D$180,2) -> 0 | F93: 182 | G93: பகீ | H93: பத்து
D94: 7 | E94: =VLOOKUP(F94,mainData_collection!$B$2:$D$180,2) ->  | F94: 293 | G94: போத்து கால் | H94: போத்து கால்
D95: 8 | E95: =VLOOKUP(F95,mainData_collection!$B$2:$D$180,2) ->  | F95: 342 | G95: ஆந்தூர் | H95: ஆங்கு
B96: P75/SN75/2029 | C96: 2029 | F96: =_xlfn.TEXTJOIN(";",TRUE,F97:F104) -> 391;391;99;59;182;293;342 | G96: கோந்தோளாதோர் சமுதாயத்திற்கு சேராபோய பத்து போத்து கால் முக்கியமாகும் | H96: கொந்தள தேச மக்களுக்கும் சேராமான் முனிக்கும் பத்து பற்று வைத்தது பத்து போத்து கால் கரும்பு தோட்டம்
E97: =VLOOKUP(F97,mainData_collection!$B$2:$D$180,2) ->  | F97: 391 | G97: கோந்தோளா | H97: கொந்தள தேசம்
E98: =VLOOKUP(F98,mainData_collection!$B$2:$D$180,2) ->  | F98: 391 | G98: கோந்தோளா | H98: மக்களுக்கு
E99: =VLOOKUP(F99,mainData_collection!$B$2:$D$180,2) ->  | F99: 99 | G99: நோர் | H99: உம்
E100: =VLOOKUP(F100,mainData_collection!$B$2:$D$180,2) ->  | F100: 59 | G100: சேராபோய | H100: சேராமான் முனிக்கும்
E101: =VLOOKUP(F101,mainData_collection!$B$2:$D$180,2) -> 0 | F101: 182 | G101: பகீ | H101: பத்து பற்று
E102: =VLOOKUP(F102,mainData_collection!$B$2:$D$180,2) ->  | F102: 293 | G102: போத்து கால் | H102: போத்து கால் கரும்பு தோட்டம்
...

Sheet processd_Yajana_Mathiazhgan
G1: IM_Ref_No_RightToLeft | I1: IM_No_and_Script | J1: IM_Script_No | M1: IM_Script_No | N1: IM_No_and_Script | O1: யஜனதேவம், கங்காளி, மதிவாணன், மதியழகன், பூரண சந்திரன், எனது ஆரம்ப நிலையில் என பலரின் எண்ணங்களின் வளரும் தொகுப்பு | P1: யஜனதேவம் வழியில் அகர வரிசை குறிப்பு | Q1: மதியழகன் வழியில் அகர குறிப்பு
G2: 1 | J2: 1 | K2: =VLOOKUP(J2,mainData_collection!$B$2:$E$132,2,FALSE) ->  | L2:  | M2: 1 | O2: ஆயு மனிதன் ஆள் அவன் கடவுள் அய்யன், காவலாளி, கோ - தலைவன் | P2: அ | Q2: ஆள்/ஆர்
G3: 3 | J3: 3 | K3: =VLOOKUP(J3,mainData_collection!$B$2:$E$132,2,FALSE) -> #N/A | M3: 3
G4: 15 | J4: 15 | K4: =VLOOKUP(J4,mainData_collection!$B$2:$E$132,2,FALSE) ->  | L4:  | M4: 15 | O4: யவக்ஷ்ரிஷ்தி தானிய வியாபாரி நெய் எண்ணெய் வியாபாரி தூக்கு தூக்கி யாதவன் | P4: ய | Q4: காவிதியன்/காட்டுவன்
G5: 29 | J5: 29 | K5: =VLOOKUP(J5,mainData_collection!$B$2:$E$132,2,FALSE) -> #N/A | M5: 29 | Q5: காவிதி/காட்டி
G6: 48 | J6: 48 | K6: =VLOOKUP(J6,mainData_collection!$B$2:$E$132,2,FALSE) ->  | L6:  | M6: 48 | O6: சாக்காரா அணில் குறிஞ்சி உதயம் மொட்டு மலர் மகரந்தம் விந்து தாமரை பருத்தி | P6: ச | Q6: குற/குறவன்
G7: 53 | J7: 53 | K7: =VLOOKUP(J7,mainData_collection!$B$2:$E$132,2,FALSE) ->  | L7:  | M7: 53 | O7: ஹ ஸ பாக்கு வெட்டி கத்திரி குழந்தை நண்டு கொடுக்கு | P7: ஹ | Q7: பாடி /பாடு
G8: 59 | J8: 59 | K8: =VLOOKUP(J8,mainData_collection!$B$2:$E$132,2,FALSE) ->  | L8:  | M8: 59 | O8: ம, மீ, மீன், முனி , பேன், பெண் | P8: ம | Q8: ப,பா,பு
G9: 59 | J9: 65 | K9: =VLOOKUP(J9,mainData_collection!$B$2:$E$132,2,FALSE) ->  | L9:  | M9: 65 | O9: அன்ங்க்க மீன் அம் மீன் அம்மான் அமர் தலைமை பூசாரி பேய் போயா போய் | P9: அம | Q9: தலைப்பா
G10: 59 | J10: 67 | K10: =VLOOKUP(J10,mainData_collection!$B$2:$E$132,2,FALSE) ->  | L10:  | M10: 67 | O10: மத்திய மீன் நீர் சிலந்தி புழு புலி பூசாரி போயா தலை பிரட்டை | P10: ம | Q10: புல /புலி
G11: 59 | J11: 72 | K11: =VLOOKUP(J11,mainData_collection!$B$2:$E$132,2,FALSE) -> #N/A | M11: 72 | Q11: ப,பா,பு
G12: 59 | J12: 86 | K12: =VLOOKUP(J12,mainData_collection!$B$2:$E$132,2,FALSE) ->  | L12:  | M12: 86 | O12: அ அச் அச்சு அடி அசித் அசி ஜானி கோல் அடி கோல் | P12: அ | Q12: அ
G13: 65 | J13: 87 | K13: =VLOOKUP(J13,mainData_collection!$B$2:$E$132,2,FALSE) ->  | L13:  | M13: 87 | O13: சோப்னா ஏணி இரு கோடுகள் ஈர்க்கு குச்சிகள் இரண்டு இணை | P13: ச | Q13: இ /இல்/இன்
G14: 65 | J14: 89 | K14: =VLOOKUP(J14,mainData_collection!$B$2:$E$132,2,FALSE) ->  | L14:  | M14: 89 | O14: ஜரா நீர்வீழ்ச்சி நதி ஆறு ஜலம் நீர் மூன்று விபூதி பட்டை மூன்று உலகம் ஞாலம் அடுக்கு அலை வழி | P14: ஜ | Q14: ம/முன்
G15: 67 | J15: 99 | K15: =VLOOKUP(J15,mainData_collection!$B$2:$E$132,2,FALSE) ->  | L15:  | M15: 99 | O15: வி இரண்டு கொக்கி வகூத்தல் மீதி விகுதி தோர் தார் | P15: வ | Q15: இ /இல்/இன்
G16: 72 | J16: 102 | K16: =VLOOKUP(J16,mainData_collection!$B$2:$E$132,2,FALSE) -> #N/A | M16: 102 | Q16: ம/முன்
G17: 86 | J17: 104 | K17: =VLOOKUP(J17,mainData_collection!$B$2:$E$132,2,FALSE) -> #N/A | M17: 104 | Q17: ந , நா, நல்
G18: 87 | J18: 119 | K18: =VLOOKUP(J18,mainData_collection!$B$2:$E$132,2,FALSE) -> #N/A | M18: 119
G19: 87 | J19: 121 | K19: =VLOOKUP(J19,mainData_collection!$B$2:$E$132,2,FALSE) ->  | L19:  | M19: 121 | O19: சஞ்ஜான் மழை காற்று ஜலம் | P19: ஜ | Q19: பண் / பன்னீர்
G20: 89 | J20: 136 | K20: =VLOOKUP(J20,mainData_collection!$B$2:$E$132,2,FALSE) -> #N/A | M20: 136
G21: 89 | J21: 146 | K21: =VLOOKUP(J21,mainData_collection!$B$2:$E$132,2,FALSE) ->  | L21:  | M21: 146 | O21: 0 | P21: 0
G22: 89 | J22: 162 | K22: =VLOOKUP(J22,mainData_collection!$B$2:$E$132,2,FALSE) -> #N/A | M22: 162 | Q22: ன /நல்/தினை
G23: 99 | J23: 169 | K23: =VLOOKUP(J23,mainData_collection!$B$2:$E$132,2,FALSE) ->  | L23:  | M23: 169 | O23: ரத்தர் பாம்பு அரிவாள் விரல் மரம் | P23: ர | Q23: ன /நல்/தினை
G24: 99 | J24: 171 | K24: =VLOOKUP(J24,mainData_collection!$B$2:$E$132,2,FALSE) ->  | L24:  | M24: 171 | O24: தார்து தூக்கு மரம் தீ பந்தம் கை விரல் கீறி கிளரி மரம் கொடி கம்பம். | P24: த | Q24: கழி/களி
G25: 99 | J25: 175 | K25: =VLOOKUP(J25,mainData_collection!$B$2:$E$132,2,FALSE) ->  | L25:  | M25: 175 | O25: சத்தர காளான் நாமம் பறந்து விழும் விதை மரம் முலை மலர் சுழலும் விதை | P25: ச | Q25: வித்து / விதை
G26: 102 | J26: 176 | K26: =VLOOKUP(J26,mainData_collection!$B$2:$E$132,2,FALSE) ->  | L26:  | M26: 176 | O26: இஷிக புல்கட்டு ஈறு ஈ இ பல் காட்டு சீப்பு கீறி பயிர் நாற்று | P26: இ | Q26: கை
G27: 104 | J27: 177 | K27: =VLOOKUP(J27,mainData_collection!$B$2:$E$132,2,FALSE) ->  | L27:  | M27: 177 | O27: இசீக்கா புல் கட்டு திண்பண்டம் கதிர் சுனை சோளம் திரி பின்னல். | P27: இ
G28: 119 | J28: 182 | K28: =VLOOKUP(J28,mainData_collection!$B$2:$E$132,2,FALSE) -> 0 | L28: 0 | M28: 182 | O28: மாயா குதிரை நாய் விலங்கு மண் குதிரை | P28: m
G29: 121 | J29: 183 | K29: =VLOOKUP(J29,mainData_collection!$B$2:$E$132,2,FALSE) -> #N/A | M29: 183
G30: 136 | J30: 192 | K30: =VLOOKUP(J30,mainData_collection!$B$2:$E$132,2,FALSE) -> 0 | L30: 0 | M30: 192 | O30: மந்திரா குடியிருப்பு குடில் வீடு தொப்பி கொம்பு மந்திர் கோயில் மாடம் | P30: ம | Q30: அறவ/அற
G31: 146 | J31: 193 | K31: =VLOOKUP(J31,mainData_collection!$B$2:$E$132,2,FALSE) ->  | L31:  | M31: 193 | O31: 0 | P31: 0 | Q31: அறவ/அற
G32: 162 | J32: 195 | K32: =VLOOKUP(J32,mainData_collection!$B$2:$E$132,2,FALSE) -> #N/A | M32: 195 | Q32: கலை, ஏகலை
G33: 169 | J33: 197 | K33: =VLOOKUP(J33,mainData_collection!$B$2:$E$132,2,FALSE) ->  | L33:  | M33: 197 | O33: மிரிக்ஷா சீப்பு மாடி வீடு தூண் திட்டு மேடு | P33: ம | Q33: மர/மாட
G34: 171 | J34: 204 | K34: =VLOOKUP(J34,mainData_collection!$B$2:$E$132,2,FALSE) ->  | L34:  | M34: 204 | O34: அக மாலை கூம்பு படி கோயில் | P34: அ | Q34: மருத
G35: 175 | J35: 211 | K35: =VLOOKUP(J35,mainData_collection!$B$2:$E$132,2,FALSE) ->  | L35:  | M35: 211 | O35: நாலிக்கா அம்பு ஈட்டி முருகன் வேலன் நல்லான் காத்தவராயன் கோபுரம் குடில் | P35: ந | Q35: ஆர்
G36: 176 | J36: 216 | K36: =VLOOKUP(J36,mainData_collection!$B$2:$E$132,2,FALSE) ->  | L36:  | M36: 216 | O36: அஷ்டபாசு எட்டுக் கால் சிலந்தி குழந்தை பாக்கு வெட்டி கத்திரி சிலந்தி தேள் கொடுக்கு நண்டு | P36: அஸ் | Q36: கூத்த / கூட
G37: 176 | J37: 229 | K37: =VLOOKUP(J37,mainData_collection!$B$2:$E$132,2,FALSE) -> #N/A | M37: 229
G38: 176 | J38: 230 | K38: =VLOOKUP(J38,mainData_collection!$B$2:$E$132,2,FALSE) ->  | L38:  | M38: 230 | O38: தன்த பற்கள் மலை முகடுகள் வீடுகள் மரங்கள் கிராமம் | P38: த | Q38: மலை
G39: 176 | J39: 233 | K39: =VLOOKUP(J39,mainData_collection!$B$2:$E$132,2,FALSE) -> 0 | L39: 0 | M39: 233 | O39: ஷிக்கா மயில் கொண்டை மலர் மலை வீடு மேடு கிராம வீடுகள் | P39: ச | Q39: மலை
G40: 177 | J40: 244 | K40: =VLOOKUP(J40,mainData_collection!$B$2:$E$132,2,FALSE) -> 0 | L40: 0 | M40: 244 | O40: தாடய மேளம் பாத்தி கிராமம் வீடுகள் கிணறு குளம் வரைவு | P40: த
G41: 182 | J41: 293 | K41: =VLOOKUP(J41,mainData_collection!$B$2:$E$132,2,FALSE) -> #N/A | M41: 293 | Q41: காவல்/கா
G42: 182 | J42: 328 | K42: =VLOOKUP(J42,mainData_collection!$B$2:$E$132,2,FALSE) -> #N/A | M42: 328 | Q42: அள /அளவ
G43: 183 | J43: 336 | K43: =VLOOKUP(J43,mainData_collection!$B$2:$E$132,2,FALSE) -> 0 | L43: 0 | M43: 336 | O43: அம்சு அன்சு விளக்கு நாமம் செக்கு பானை சட்டி உலக்கை உரல் உலக்கை பூ மகரந்தம் | P43: ந | Q43: வழி/வரு
G44: 192 | J44: 341 | K44: =VLOOKUP(J44,mainData_collection!$B$2:$E$132,2,FALSE) -> 0 | L44: 0 | M44: 341 | O44: தான கலம் கூஜா உலைக்கலம் | P44: த
G45: 193 | J45: 342 | K45: =VLOOKUP(J45,mainData_collection!$B$2:$E$132,2,FALSE) ->  | L45:  | M45: 342 | O45: அன் அம்சு சோம பானம் ஆ பசு ஆந்தை அமுதம் மழை, கிணறு, பள்ளம், கோ, அண்டா, மரக்கால் , ஆனா, ஆம், அந்த, ஆந்த, ஆந்தை, அது, இருப்பது, மாடு, மந்தை | P45: அன் | Q45: ன்/ஆன்
G46: 195 | J46: 343 | K46: =VLOOKUP(J46,mainData_collection!$B$2:$E$132,2,FALSE) -> #N/A | M46: 343
G47: 197 | J47: 344 | K47: =VLOOKUP(J47,mainData_collection!$B$2:$E$132,2,FALSE) -> #N/A | M47: 344
G48: 204 | J48: 375 | K48: =VLOOKUP(J48,mainData_collection!$B$2:$E$132,2,FALSE) -> #N/A | M48: 375
G49: 211 | J49: 387 | K49: =VLOOKUP(J49,mainData_collection!$B$2:$E$132,2,FALSE) ->  | L49:  | M49: 387 | O49: சுக்ரா விதை கரு சிவன் முட்டை முறை பயிர் பருப்பு | P49: ச | Q49: புற/பற
G50: 211 | J50: 391 | K50: =VLOOKUP(J50,mainData_collection!$B$2:$E$132,2,FALSE) ->  | L50:  | M50: 391 | O50: ரத்தாரின் சக்கரம் கொந்தளம் கோந்தாளம் மேளம் தாளம் வட்டம் ஆரம்ப சுற்று அன் ஆன் வான் சூரியன் நட்சத்திரம் | P50: ர | Q50: நடு, ணஆடு
G51: 216 | J51: 403 | K51: =VLOOKUP(J51,mainData_collection!$B$2:$E$132,2,FALSE) ->  | L51:  | M51: 403 | O51: தானக்கா காசு பணம் வளையல் காப்பு அக்காமார் | P51: த | Q51: கண்/முக்கண்
G52: 229
G53: 230
G54: 230
G55: 233
G56: 244
G57: 244
G58: 293
G59: 293
G60: 328
G61: 336
G62: 336
G63: 336
... G84: 403
G102: IM_Ref_No_RightToLeft

Sheet Dholavira_puru
C2: Description | D2: L1 | E2: L2 | F2: L3 | G2: L4 | H2: L5 | I2: L6 | J2: L7 | K2: L8 | L2: L9 | M2: L10
C3: Script Sign
C4: Script ID IM77 | D4: 391 | E4: 256 | F4: 327 | G4: 391 | H4: 261 | I4: 134 | J4: 86 | K4: 391 | L4: 391 | M4: 53
C5: Purushothaman | D5: (irungovin) arasaanai therivippathu – vanigar, payanikalukku thangum idam – thalaiyaari kottai – This is by order of King(Irungo) – his captain’s fort – providing shelter, water, food and goods transport protection – thOL vira (Dholavira), the soldiers
C7: Description | D7: Script Sign | E7: Script ID IM77 | F7: Description of the script | G7: alphabetic - ccandidates | H7: syllabic candidates | I7: words - candidates
C8: L1 | E8: 391 | F8: wheel, seat, Community Kondala, Time, Drum, country, சக்கரம், கொந்தளம் மேடை, கோந்தலாம் அரசு, காலம், கால சக்கரம், அரசு மத்தளம் , சூரியன், ஓட்டம், சுற்று | G8: cha, ko, ka, ச, க, கோ | H8: kO, கோ | I8: arasa murasu, maattu vandi chakkaram, அரசு முரசு, சக்கரம்
C9: L2 | E9: 256 | F9: thread bundle, hammer, drum stick, order, நூல் கண்டு, சுத்தி, கொட்டும் கருவி, ஆணை | G9: tha, aa, noo, த, நூ, சு, ஆ | H9: aanai, ஆணை, அடி, தெரி | I9: aanai, ஆணை, அடி, தெரி
C10: L3 | E10: 327 | F10: queen, king, leaf, அரசு, அரசி, அரசன், அரச இலை, தெய்வம் | G10: a, அ, ஆ , தெ | H10: arasa, அரச, தெய்வ | I10: arasi, arasan, அரசன், அரசி, தெய்வம்
C11: L4 | E11: 391 | F11: wheel, seat, Community Kondala, Time, Drum, country, சக்கரம், கொந்தளம் மேடை, கோந்தலாம் அரசு, காலம், கால சக்கரம், அரசு மத்தளம் , சூரியன், ஓட்டம், சுற்று | G11: cha, ko, ka, ச, க, கோ | H11: kO, கோ | I11: arasa murasu, maattu vandi chakkaram, அரசு முரசு, சக்கரம்
C12: L5 | E12: 261 | F12: diamond, well, fort, village, வைரம், கிணறு, சட்டம், தொழிற்சாலை, கோட்டை, புதைக்கும் இடம் , மேடை | G12: வை, கி, கோ, மே | H12: வைர, கோட்டை, மேடை | I12: kottai, kinaRu, oor, viidu, கோட்டை. கிணறு, ஊர், மேடை
C13: L6 | E13: 134 | F13: head, hut, stone edge, தலை, குடிசை, கூறிய முனை | H13: thalai | I13: viidu, kudisai, thalai, வீடு, குடிசை, தலை, மலை, கூர்மை, குவியல் | K13: 261,134.86
C14: L7 | E14: 86 | F14: stick, number one, கழி, தடி, ஒன்று, செங்கோல் | G14: aa | H14: aari, ஆரி | I14: kazi, kol, aari , control, கழி, கோல், தடி, செங்கோல், ஒன்று
C15: L8 | E15: 391 | F15: wheel, seat, Community Kondala, Time, Drum, country, சக்கரம், கொந்தளம் மேடை, கோந்தலாம் அரசு, காலம், கால சக்கரம், அரசு மத்தளம் , சூரியன், ஓட்டம், சுற்று | G15: cha, ko, ka, ச, க, கோ | H15: kO, கோ | I15: arasa murasu, maattu vandi chakkaram, அரசு முரசு, சக்கரம்
C16: L9 | E16: 391 | F16: wheel, seat, Community Kondala, Time, Drum, country, சக்கரம், கொந்தளம் மேடை, கோந்தலாம் அரசு, காலம், கால சக்கரம், அரசு மத்தளம் , சூரியன், ஓட்டம், சுற்று | G16: cha, ko, ka, ச, க, கோ | H16: kO, கோ | I16: arasa murasu, maattu vandi chakkaram, அரசு முரசு, சக்கரம்
C17: L10 | E17: 53 | F17: scissors, baby, singing, crying, crab, bullock cart, bulls, beetle, வண்டு , நண்டு, கடி, வெட்டி, மாட்டு வண்டி பூட்டு, மாட்டு கொம்பு | G17: வ,, ந , டி, வெ , பூ | I17: irattai maadu, madu kombu, vandi, இரட்டை மாட்டு வண்டி, பயணிகள், பொருள் | K17: 391,391,53
C18: L1L2L3L4 | D18: ideagraph | E18: 391,256,327.391 | F18: by royal order, அரச கட்டளை | G18: அரச | H18: royal drum, அரசு மேளம், அடிப்பது, தெரிவிப்பது | I18: arasa aanai, அரசு ஆணை, கட்டளை, முரசு தெரிவிப்பது
C19: L5L6L7 | D19: ideagraph | E19: 261,134.86 | F19: the head of the fort, கோட்டையின் தலையாரி | I19: the head of the fort, கோட்டையின் தலையாரி
C20: L8L9L10 | D20: ideagraph | E20: 391,391,53 | F20: travellers, transporters, வணிகர், வியாபாரிகள், பொருள் ஏற்றி செல்பவர்கள் | I20: travellers, transporters, வணிகர், வியாபாரிகள், பொருள் ஏற்றி செல்பவர்கள்
C21: L1-L10 | D21: interpretaion and explanatory note, நான் படித்த வகையில் | F21: இருங்கோவின் ஆணை - இது அவனின் தலையாரியின் கோட்டை - இங்கு தங்கலாம் சத்திர வசதி, வண்டி எடுத்து செல்ல, பாதுகாப்பு அளிக்கப்படுகிறது. இது கோந்தாளா கோயா மக்களின் சமுதாயத்தின் கூட்டமைப்பு all facilities are provided to travellers, transporters including protection of food, wter, food and stay through Kondaalaa King's order and the guild of the business people and the Koya community. இது இன்றும் இந்த நகரம் டோலாவிர என்று அறியப்படுவது தமிழ சங்க கள இலக்கியங்கள் வழியாக வணிகருக்கும் அரசர்களுக்கும் இருந்து ஒற்றுமை தொடர்பை காட்டுவதாக காணலாம், தொளவிரா என்பதை தோள் வீரர என்று தமிழில் காண புலப்படும். We can easily connect this place name Dholavira if we connect to what is mentioed in Tamil Sangam literature as the good relationship between business people and the king and take the idea conveyed by this wall sign, place name and in Tamil form, if we see as tHoL Vira that means the soldiers who helped protect and transport the goods. This fort could have acted both as a public resting traditional Chaththiram and goods transition point. Note the leaf crowing decoration and the wheel signs indicating transport as critical to read this wall sign as above.

Sheet M314
C1: M-134 | D1: யஜன தேவம் | E1: கங்காளி | F1: பிரபுநாத் ஹேமப்ரான் | H1: எனது கருத்து
C2: சின்னங்கள் | I2: Sign No | J2: Signs | K2: யஜன தேவம் | L2: கங்காளி | M2: பிரபுநாத் ஹேமப்ரான் | O2: எனது கருத்து
A3: 391 | D3: ர, | E3: கோந்தோளா | F3: அவில்.. கை உயர்த்தி கும்பிட | H3: கோந்தளத்தோர் | I3: M391 | K3: ர, | L3: கோந்தோளா | M3: அவில்.. கை உயர்த்தி கும்பிட | O3: கோந்தளத்தோர், சூரிய குலத்தோர், மக்கள்
H4: சூரிய குலத்தோர் | I4: M99 | K4: வ, இரவ | L4: தோர் கோந்தாள சமூகத்தோர் | M4: லகு லகா .. மந்திரம் உச்சரிக்க
H5: மக்கள் | I5: M65 | K5: ம, | L5: தலாபோய தலைமை பூசாரி | M5: சின் பங்கா .. சூரிய தெய்வம் | O5: மூன்று முனிகளையும் நட்சித்திரங்களையும் மும்மூர்திகளையும் வணங்கி
D6: வ, | E6: தோர் | F6: லகு லகா .. மந்திரம் உச்சரிக்க | I6: M67 | K6: ம, | L6: முட்டவாபோயதா முதல் பூசாரி | M6: ஜாகர் ஏரா போங்கா.. பெண் தெய்வங்களும் காடுகளும்
D7: இரவ | E7: கோந்தாள சமூகத்தோர் | I7: M211 | K7: ந, மனா மதிப்புள்ள | L7: ஆரதே சக்தி (வேல் துணையோடு) | M7: வேட்டைக்கு விழாவிற்கு | O7: வேலனை வணங்கி
D8: கர்ஜிக்கும் | I8: M105 | K8: ச, | L8: நால நல்ல | M8: லகு லகா நான்கு புறமும் சிறக்க காக்க | O8: மக்கள் நலம் காத்து
D9: ம, | E9: தலாபோய | F9: சின் பங்கா .. சூரிய தெய்வம் | H9: மூன்று முனிகளையும் நட்சித்திரங்களையும் மும்மூர்திகளையும் வணங்கி | I9: M129 | K9: க, | L9: கோரி ஏர் விவசாயி | M9: கின்டெட் மன்டெட் விழுந்து விழுந்து வணங்கி | O9: விவசாயிகள்
E10: தலைமை பூசாரி | I10: M336 | K10: ந, | L10: நுறு நொறுக்குசெக்கு எண்ணெய் பானை | M10: ஹண்டி.. பச்சை தைலம் | O10: வாணியர்
D11: ம, | E11: மூரா போய | F11: மொரெகோ துருய்கோ.. பல தெய்வங்கள் | I11: M347 | K11: ர, | L11: நேராள நெல் பயிர் ஆள் | M11: தரக் தரக் மரம் | O11: காடு வளம்
D12: அமாம் | I12: M342 | K12: அன், நாரம் மனிதர் | L12: ஆனா ஆவினம் மாடு ஆடு | M12: தகனோ.. கை உயர்த்தி கும்பிட்டு | O12: ஆடு மாடு வளம் பேணி
D13: சக்தியுள்ள | E13: குரு பூசாரி | I13: M89 | K13: ஜ, | L13: மூன மூன்று | M13: பே மகா .. உதயத்திற்கு பிறகு | O13: முக்காலமும்
D14: ம, | E14: முட்டவாபோயதா | F14: ஜாகர் ஏரா போங்கா.. பெண் தெய்வங்களும் காடுகளும் | I14: M381 | K14: த, | L14: போல்லி புள்ளி (புலி மேளம்) | M14: மன்டெர்.. மேளம் தாளத்தோடு | O14: கொட்டு மேளம் கொட்டு
E15: முதல் பூசாரி | I15: M180 | K15: ல, ஜத்தலா கடல் போன்ற | L15: மர்ரீ (வகையரா) குழந்தைகள் மக்கள் | M15: சோகோ.. இசைக்கருவி இசைத்து | O15: வழி வழியாக வரும் நீர் வளம்
D16: ந, | E16: ஆரதே | F16: வேட்டைக்கு விழாவிற்கு | H16: வேலனை வணங்கி | I16: M307 | K16: த, | L16: வில்லம்பாள் வில் அம்பு ஆள் | M16: சேந்தரா சேகர் - வில் அம்போடு.. | O16: வில் தொழில்
D17: மனா | E17: சக்தி (வேல் துணையோடு) | I17: M1 | K17: அ, | L17: ஆள் | O17: காவல் தொழில்
D18: மதிப்புள்ள | I18: M1361 | K18: ச, | L18: போத்துகோட் (கோதுமை) | M18: போன்டி பாஜ்கோ பான்டோ - விலங்கு விழ குழி பறித்து | O18: நெல் கோதுமை உணவு
D19: ச, | E19: நால | F19: லகு லகா நான்கு புறமும் சிறக்க காக்க | H19: மக்கள் நலம் காத்து | I19: M1022 | K19: ஹ வஹ அளிப்பவனே | L19: பில்கேசீர (தலை சிறந்தவர்) | M19: சிறிய விலங்குகள் (பிடிப்பார்கள்) | O19: தலை சிறந்து சிந்திப்பீர்
E20: நல்ல | U20: M391 | V20: M99 | W20: M65 | X20: M67 | Y20: M211 | Z20: M105 | AA20: M129 | AB20: M336 | AC20: M347 | AD20: M342 | AE20: M89 | AF20: M381 | AG20: M180 | AH20: M307 | AI20: M1 | AJ20: M1361 | AK20: M1022
D21: க, | E21: கோரி | F21: கின்டெட் மன்டெட் விழுந்து விழுந்து வணங்கி | H21: விவசாயிகள்
E22: ஏர் விவசாயி
D23: ச, | E23: நால | F23: லகு லகா நான்கு புறமும் சிறக்க காக்க
D24: சக்சா | E24: நல்ல
D25: சக்தியுள்ள
D26: ந, | E26: நுறு | F26: ஹண்டி.. பச்சை | H26: வாணியர்
E27: நொறுக்குசெக்கு எண்ணெய் பானை | F27: தைலம்
F28: அரைத்து தடவி
D29: ர, | E29: நேராள | F29: தரக் தரக் மரம் | H29: காடு வளம்
E30: நெல் பயிர் ஆள்
D31: அன், | E31: ஆனா | F31: தகனோ.. கை உயர்த்தி கும்பிட்டு | H31: ஆடு மாடு வளம்
D32: நாரம் | E32: ஆவினம் | H32: பேணி
D33: மனிதர் | E33: மாடு ஆடு
D34: ஜ, | E34: மூன | F34: பே மகா .. உதயத்திற்கு பிறகு | H34: முக்காலமும்
E35: மூன்று
D36: த, | E36: போல்லி | F36: மன்டெர்.. மேளம் தாளத்தோடு | H36: கொட்டு மேளம் கொட்டு
E37: புள்ளி (புலி மேளம்)
D38: ல, | E38: மர்ரீ | F38: சோகோ.. இசைக்கருவி இசைத்து | H38: வழி வழியாக வரும் நீர் வளம்
E39: (வகையரா) குழந்தைகள் மக்கள்
D40: ஜத்தலா
D41: கடல் போன்ற
D42: த, | E42: வில்லம்பாள் | F42: சேந்தரா சேகர் - வில் அம்போடு.. | H42: வில் தொழில்
E43: வில் அம்பு ஆள்
D44: அ, | E44: ஆள் | H44: காவல் தொழில்
D45: ர, | E45: ஓமாள் | H45: பயிர் தொழில்
D46: தாரா | E46: நெல் பயிர் கதிர்
D47: காப்பாற்றும்
D48: ச, | E48: போத்துகோட் | F48: போன்டி பாஜ்கோ பான்டோ - விலங்கு விழ குழி பறித்து | H48: நெல் கோதுமை உணவு
E49: (கோதுமை)
D50: ஹ | E50: பில்கேசீர | F50: சிறிய விலங்குகள் (பிடிப்பார்கள்) | H50: தலை சிறந்து சிந்திப்பீர்
E51: (தலை சிறந்தவர்)
D52: வஹ
D53: அளிப்பவனே

Sheet M314 refined
H1: M391, M99, M65, M67, M211, M105, M129, M336, M347, M342, M89, M381, M180, M307, M1, M1361, M1022
A2: Position from Right | B2: signs_vari | C2: Sign No | D2: Signs | E2: Position from Right | F2: Script Sign | G2: Script ID IM77 | H2: யஜன தேவம் | I2: கங்காளி | J2: பிரபுநாத் ஹேமப்ரான் | K2: எனது கருத்து | L2: ராஜ் ஸ்ரீ | M2: ராஜ் ஸ்ரீ +நான் கருதுவதும் | S2: யஜன தேவம் | T2: ர, | V2: Scholars | W2: interpretation / reading indus seal m-314 | Z2: context | AA2: IM77 script 391
A3: Seal_M314_R1 | C3: M391 | E3: Seal_M314_R1 | G3: 391 | H3: ர, | I3: கோந்தோளா | J3: அவில்.. கை உயர்த்தி கும்பிட | K3: கோந்தளத்தோர் சூரிய குலத்தோர் மக்கள் | L3: வாய் | M3: வாய், வாக்கு, உறுதி , வாய்மை | S3: கங்காளி | T3: கோந்தோளா | V3: யஜன தேவம் | W3: “ Honour the powerful roarer O sustainer, O ocean (Shiva) yield to the capable man” relting to Rig Veda: RV 5.45.10 “ hearing him, the waters receded" | Z3: religious vedic | AA3: ர,
A4: Seal_M314_R2 | C4: M99 | E4: Seal_M314_R2 | G4: 99 | H4: வ, இரவ | I4: தோர் கோந்தாள சமூகத்தோர் | J4: லகு லகா .. மந்திரம் உச்சரிக்க | L4: தூ | M4: தூ, ஆவது | S4: பிரபுநாத் ஹேமப்ரான் | T4: அவில்.. கை உயர்த்தி கும்பிட | V4: கங்காளி | W4: समुदाय के सिरष मुखिया प्रधान मुखिया गुरु मुखिया की सत्ता में ; अच्छे कृषक और अच्छे कुठाई भंडारी का ; प्रथम शेर पुत्र विलंबाल ओमाल पोतूकोट बिलकेशीर” :: "Under the leadership of the community's supreme chief, a wise and just ruler, the illustrious son of a virtuous farmer and a prudent storekeeper, Vilambal Omal Fotukot Vilakeshir, shines forth like a lion." | Z4: religious and community | AA4: கோந்தோளா
A5: Seal_M314_R3 | C5: M65 | E5: Seal_M314_R3 | G5: 65 | H5: ம, | I5: தலாபோய தலைமை பூசாரி | J5: சின் பங்கா .. சூரிய தெய்வம் | K5: மூன்று முனிகளையும் நட்சித்திரங்களையும் மும்மூர்திகளையும் வணங்கி | L5: நீ | M5: நீ, இதனி, இதனால் | S5: எனது கருத்து | T5: கோந்தளத்தோர் சூரிய குலத்தோர் மக்கள் | V5: பிரபுநாத் ஹேமப்ரான் | W5: “ With raised arms and looking up, operate spell and worship Siń bạṅgạ, Mo͂ṛe͂ko Turuiko bạṅgạ and Jaher era bạṅgạ in Disom Sendra, and hobbling, operate spell in the four directions and offer libation with prayer for continuous absolute safety and musicians play sogoe during the three days and the hunters look for the victimised animals in the trap.” | Z5: religious and community | AA5: அவில்.. கை உயர்த்தி கும்பிட
A6: Seal_M314_R4 | C6: M67 | E6: Seal_M314_R4 | G6: 67 | H6: ம, | I6: முட்டவாபோயதா முதல் பூசாரி | J6: ஜாகர் ஏரா போங்கா.. பெண் தெய்வங்களும் காடுகளும் | L6: மா | M6: ம | S6: ராஜ் ஸ்ரீ | T6: வாய் | V6: எனது கருத்து - based on religious tone | W6: கோந்தளத்தோர் சூரிய குலத்தோர் மக்கள் ++மூன்று முனிகளையும் நட்சித்திரங்களையும் மும்மூர்திகளையும் வணங்கி ++வேலனை வணங்கி ++மக்கள் நலம் காத்து ++விவசாயிகள் ++மக்கள் நலம் காத்து ++வாணியர் ++காடு வளம் ++ஆடு மாடு வளம் பேணி ++முக்காலமும் ++கொட்டு மேளம் கொட்டு ++வழி வழியாக வரும் நீர் வளம் ++வில் தொழில் ++காவல் தொழில் ++நெல் கோதுமை உணவு ++தலை சிறந்து சிந்திப்பீர் | Z6: community and parising nature | AA6: கோந்தளத்தோர் சூரிய குலத்தோர் மக்கள்
A7: Seal_M314_R5 | C7: M59 | E7: Seal_M314_R5 | G7: 59 | H7: ம, | I7: முட்டவாபோயதா முதல் பூசாரி | J7: ஜாகர் ஏரா போங்கா.. பெண் தெய்வங்களும் காடுகளும் | L7: நா, னா | M7: ன, நியமனம் , நிர்மாணிக்க | S7: ராஜ் ஸ்ரீ +நான் கருதுவதும் | T7: வாய், வாக்கு, உறுதி , வாய்மை | V7: ராஜ் ஸ்ரீ | W7: Vai — by/indeed — cause/summons — declaration — of the person — statement clause::“By Vai is declared the cause and summons; the person now issues a formal statement or vow.”; Contract / bond — binding term — of / by — default or loss — then / if :: If the contractual bond is broken, then the penalty or loss clause shall apply.; These — wealth — principal / root — farmland (pledged) — and — house — property / estate. :: “These constitute the pledged assets: wealth as principal, farmland, and household property forming the estate.” | Z7: loan agreement | AA7: வாய்
A8: Seal_M314_R6 | C8: M211 | E8: Seal_M314_R6 | G8: 211 | H8: ந, மனா மதிப்புள்ள | I8: ஆரதே சக்தி (வேல் துணையோடு) | J8: வேட்டைக்கு விழாவிற்கு | K8: வேலனை வணங்கி | L8: தீ, தீஆ | M8: தீ, தீயாக, சத்தியம், | V8: ராஜ் ஸ்ரீ சார்ந்து நான் கருதுவது as an greement on lesing | W8: வாய், வாக்கு, உறுதி , வாய்மை ++தூ, ஆவது++நீ, இதனி, இதனால் ++ம ++ன, நியமனம் , நிர்மாணிக்க ++தீ, தீயாக, சத்தியம்,++கட்டு , பந்தம் ++அனுபந்தம் , கட்டுபட ++கட்டு, பந்தம் ++சு, செ, ச .. சூழலில், நிகழ்வில் ++ஹார , தோற்றால், காரமானால் , சண்டையானால் ++அ, என்று ஆனால், ஆண்டவன் மேல் ++தீ, தீனி, மூன்று மடங்கு ++வித், வித்து தானம் ++மூல, மூலம் ++கேத்தி, நிலம், புலம், கிணறு, ஆட்கள், தண்டல் ++த, தர ++வேண்டும் ++கர், வீடு, குத்தகை ++கா, கா, வாக்கு, கை ஒப்பம், கண் ஒப்பம் கொடுக்கப்படுகிறது >> The agriculture land along with labour, seeds, water are given on lease so that three times harvest could be done under the oversight of Village chiefs and as agreed between parties; this will be the testimony for the same. | Z8: agrculture land lease and community based | AA8: வாய், வாக்கு, உறுதி , வாய்மை | AC8: =_xlfn.TEXTJOIN("::",TRUE,AA3:AA8) -> ர, ::கோந்தோளா::அவில்.. கை உயர்த்தி கும்பிட::கோந்தளத்தோர் சூரிய குலத்தோர் மக்கள் ::வாய்::வாய், வாக்கு, உறுதி , வாய்மை | AD8: Case | AE8: Collective interpretaion of script IM77 - 391
A9: Seal_M314_R7 | C9: M105 | E9: Seal_M314_R7 | G9: 105 | H9: ச, | I9: நால நல்ல | J9: லகு லகா நான்கு புறமும் சிறக்க காக்க | K9: மக்கள் நலம் காத்து | L9: பந்தம் | M9: கட்டு , பந்தம் | V9: Scholars | W9: interpretation / reading Dholavira wall sign | Z9: context | AA9: IM77 script 391 | AD9: Dholavira Wall Sign | AE9: நா, ண, ன::நடு, நாடு, நாடுவோர் ::கோந்தள சமுதாய சின்னம் ::இரு அரச மேளம், இரு மாட்டு வண்டி சக்கரம் , வணிகர், பயணியர்::r, rathārin chariot wheel
A10: Seal_M314_R8 | C10: M129 | E10: Seal_M314_R8 | G10: 129 | H10: க, | I10: கோரி ஏர் விவசாயி | J10: கின்டெட் மன்டெட் விழுந்து விழுந்து வணங்கி | K10: விவசாயிகள் | L10: அனுபந்தம் | M10: அனுபந்தம் , கட்டுபட | V10: Mathivanan | W10: நாடன் பண்ணையன் நண்பன் | Z10: தமிழ் | AA10: நா, ண, ன | AD10: Indus seal M-314 | AE10: ர, ::கோந்தோளா::அவில்.. கை உயர்த்தி கும்பிட::கோந்தளத்தோர் சூரிய குலத்தோர் மக்கள் ::வாய்::வாய், வாக்கு, உறுதி , வாய்மை
A11: Seal_M314_R9 | C11: M129 | E11: Seal_M314_R9 | G11: 129 | H11: ச, | I11: நால நல்ல | J11: லகு லகா நான்கு புறமும் சிறக்க காக்க | K11: மக்கள் நலம் காத்து | L11: பந்தம் | M11: கட்டு, பந்தம் | V11: Mathiazhagan | W11: பாடி பொருள் பெறுவோர் நாடு அரச கோட்டை | Z11: தமிழ் | AA11: நடு, நாடு, நாடுவோர் | AD11: Put together | AE11: naadu-country, nadu-fix, naaduvor - those seek, Kondala - Gondi community, kingdom, arasa mela - royal drums, sakkaram - bullock cart wheels >> travellers, business people, r, aara, rakaa - wheel, gem, garland, religious mark, respect, truth, vow, speak, sun, time
A12: Seal_M314_R10 | C12: M336 | E12: Seal_M314_R10 | G12: 336 | H12: ந, | I12: நுறு நொறுக்குசெக்கு எண்ணெய் பானை | J12: ஹண்டி.. பச்சை தைலம் | K12: வாணியர் | L12: சு, செ, ச | M12: சு, செ, ச .. சூழலில், நிகழ்வில் | V12: Kangali | W12: இரு கோந்தளத்தின் அரசன் பொட்டு கோயா கோந்தள சமுதாயத்தின் காவலன் | Z12: Gondi Community tribal culture | AA12: கோந்தள சமுதாய சின்னம் | AE12: I have added sun, time as both are seen as wheel, cyclic, moving and similar sign by Sumerian form, "AN" is taken as God and sky, this sign still can go along with Indus usage, as one more possibility. You can compare your own views and interpretaions, as now we have a multiple, meaning words, syllables, letters that we can consider as possible.
A13: Seal_M314_R11 | C13: M347 | E13: Seal_M314_R11 | G13: 347 | H13: ர, | I13: நேராள நெல் பயிர் ஆள் | J13: தரக் தரக் மரம் | K13: காடு வளம் | L13: ஹார | M13: ஹார , தோற்றால், காரமானால் , சண்டையானால் | V13: Purushothaman | W13: அரச ஆணை வணிகர் யாத்தரிகள் | Z13: intuition , Tamil | AA13: இரு அரச மேளம், இரு மாட்டு வண்டி சக்கரம் , வணிகர், பயணியர்
A14: Seal_M314_R12 | C14: M342 | E14: Seal_M314_R12 | G14: 342 | H14: அன், நாரம் மனிதர் | I14: ஆனா ஆவினம் மாடு ஆடு | J14: தகனோ.. கை உயர்த்தி கும்பிட்டு | K14: ஆடு மாடு வளம் பேணி | L14: அ | M14: அ, என்று ஆனால், ஆண்டவன் மேல் | V14: Yagna Devam | W14: gem of chosen gems - entrance | Z14: Vedic, Cryptology | AA14: r, rathārin chariot wheel | AC14: =_xlfn.TEXTJOIN("::",TRUE,AA10:AA14) -> நா, ண, ன::நடு, நாடு, நாடுவோர் ::கோந்தள சமுதாய சின்னம் ::இரு அரச மேளம், இரு மாட்டு வண்டி சக்கரம் , வணிகர், பயணியர்::r, rathārin chariot wheel
A15: Seal_M314_R13 | C15: M89 | E15: Seal_M314_R13 | G15: 89 | H15: ஜ, | I15: மூன மூன்று | J15: பே மகா .. உதயத்திற்கு பிறகு | K15: முக்காலமும் | L15: தீ | M15: தீ, தீனி, மூன்று மடங்கு
A16: Seal_M314_R14 | C16: M381 | E16: Seal_M314_R14 | G16: 381 | H16: த, | I16: போல்லி புள்ளி (புலி மேளம்) | J16: மன்டெர்.. மேளம் தாளத்தோடு | K16: கொட்டு மேளம் கொட்டு | L16: வித் | M16: வித், வித்து தானம்
A17: Seal_M314_R15 | C17: M180 | E17: Seal_M314_R15 | G17: 180 | H17: ல, ஜத்தலா கடல் போன்ற | I17: மர்ரீ (வகையரா) குழந்தைகள் மக்கள் | J17: சோகோ.. இசைக்கருவி இசைத்து | K17: வழி வழியாக வரும் நீர் வளம் | L17: மூல | M17: மூல, மூலம்
A18: Seal_M314_R16 | C18: M307 | E18: Seal_M314_R16 | G18: 307 | H18: த, | I18: வில்லம்பாள் வில் அம்பு ஆள் | J18: சேந்தரா சேகர் - வில் அம்போடு.. | K18: வில் தொழில் | L18: கேத் | M18: கேத்தி, நிலம், புலம், கிணறு, ஆட்கள், தண்டல்
A19: Seal_M314_R17 | C19: M1 | E19: Seal_M314_R17 | G19: 1 | H19: அ, | I19: ஆள் | K19: காவல் தொழில் | L19: த | M19: த, தர
A20: Seal_M314_R18 | C20: M1361 | E20: Seal_M314_R18 | G20: 1361 | L20: வேண்டும் | M20: வேண்டும்
A21: Seal_M314_R19 | C21: M1022 | E21: Seal_M314_R19 | G21: 1022 | H21: ச, | I21: போத்துகோட் (கோதுமை) | J21: போன்டி பாஜ்கோ பான்டோ - விலங்கு விழ குழி பறித்து | K21: நெல் கோதுமை உணவு | L21: கர | M21: கர், வீடு, குத்தகை
A22: Seal_M314_R20 | C22: M1400 | E22: Seal_M314_R20 | G22: 1400 | H22: ஹ வஹ அளிப்பவனே | I22: பில்கேசீர (தலை சிறந்தவர்) | J22: சிறிய விலங்குகள் (பிடிப்பார்கள்) | K22: தலை சிறந்து சிந்திப்பீர் | L22: காஹ | M22: கா, கா, வாக்கு, கை ஒப்பம், கண் ஒப்பம் கொடுக்கப்படுகிறது
J23: Scholars | K23: interpretation / reading indus seal m-314 | N23: context
J24: யஜன தேவம் | K24: “ Honour the powerful roarer O sustainer, O ocean (Shiva) yield to the capable man” relting to Rig Veda: RV 5.45.10 “ hearing him, the waters receded" | N24: religious vedic
J25: கங்காளி | K25: समुदाय के सिरष मुखिया प्रधान मुखिया गुरु मुखिया की सत्ता में ; अच्छे कृषक और अच्छे कुठाई भंडारी का ; प्रथम शेर पुत्र विलंबाल ओमाल पोतूकोट बिलकेशीर” :: "Under the leadership of the community's supreme chief, a wise and just ruler, the illustrious son of a virtuous farmer and a prudent storekeeper, Vilambal Omal Fotukot Vilakeshir, shines forth like a lion." | N25: religious and community
J26: பிரபுநாத் ஹேமப்ரான் | K26: “ With raised arms and looking up, operate spell and worship Siń bạṅgạ, Mo͂ṛe͂ko Turuiko bạṅgạ and Jaher era bạṅgạ in Disom Sendra, and hobbling, operate spell in the four directions and offer libation with prayer for continuous absolute safety and musicians play sogoe during the three days and the hunters look for the victimised animals in the trap.” | N26: religious and community
J27: எனது கருத்து - based on religious tone | K27: கோந்தளத்தோர் சூரிய குலத்தோர் மக்கள் ++மூன்று முனிகளையும் நட்சித்திரங்களையும் மும்மூர்திகளையும் வணங்கி ++வேலனை வணங்கி ++மக்கள் நலம் காத்து ++விவசாயிகள் ++மக்கள் நலம் காத்து ++வாணியர் ++காடு வளம் ++ஆடு மாடு வளம் பேணி ++முக்காலமும் ++கொட்டு மேளம் கொட்டு ++வழி வழியாக வரும் நீர் வளம் ++வில் தொழில் ++காவல் தொழில் ++நெல் கோதுமை உணவு ++தலை சிறந்து சிந்திப்பீர் | N27: community and parising nature
J28: ராஜ் ஸ்ரீ | K28: Vai — by/indeed — cause/summons — declaration — of the person — statement clause::“By Vai is declared the cause and summons; the person now issues a formal statement or vow.”; Contract / bond — binding term — of / by — default or loss — then / if :: If the contractual bond is broken, then the penalty or loss clause shall apply.; These — wealth — principal / root — farmland (pledged) — and — house — property / estate. :: “These constitute the pledged assets: wealth as principal, farmland, and household property forming the estate.” | N28: loan agreement
J29: ராஜ் ஸ்ரீ சார்ந்து நான் கருதுவது as an greement on lesing | K29: வாய், வாக்கு, உறுதி , வாய்மை ++தூ, ஆவது++நீ, இதனி, இதனால் ++ம ++ன, நியமனம் , நிர்மாணிக்க ++தீ, தீயாக, சத்தியம்,++கட்டு , பந்தம் ++அனுபந்தம் , கட்டுபட ++கட்டு, பந்தம் ++சு, செ, ச .. சூழலில், நிகழ்வில் ++ஹார , தோற்றால், காரமானால் , சண்டையானால் ++அ, என்று ஆனால், ஆண்டவன் மேல் ++தீ, தீனி, மூன்று மடங்கு ++வித், வித்து தானம் ++மூல, மூலம் ++கேத்தி, நிலம், புலம், கிணறு, ஆட்கள், தண்டல் ++த, தர ++வேண்டும் ++கர், வீடு, குத்தகை ++கா, கா, வாக்கு, கை ஒப்பம், கண் ஒப்பம் கொடுக்கப்படுகிறது >> The agriculture land along with labour, seeds, water are given on lease so that three times harvest could be done under the oversight of Village chiefs and as agreed between parties; this will be the testimony for the same. | N29: agrculture land lease and community based

Sheet working_Kngali_puru
A1: IM_Ref_No_RightToLeft | B1: Kangali | C1: Puru
A2: 1 | B2: ஆள் | C2: கடவுள், அந்நாள்
A3: 3 | B3: ஆள் | C3: ஆள்
A4: 15 | B4: காவடியாள் ஆந்த | C4: காவடி, பால் காரர், தீவனம் அளிப்பவர் , மாட்டு பட்டி காவலர்
A5: 29 | B5: இர்பில் அம்பாள் | C5: இரட்டை மாடு பூட்டிய
A6: 48 | B6: பருத்தி | C6: மலை தேன், மலர்,
A7: 53 | B7: போத்து கோயா | C7: போத்து கோயா கரும்பு விளைச்சல் சமுதாயம்
A8: 59 | B8: பெண், பேன் | C8: மீன், முனி, நீர் சிலந்தி,போர்த்திய ஆள் பெண், புழு, புலி
A9: 59 | B9: முட்டவா போய | C9: முனிவர், முதலாம் குரு
A10: 59 | B10: முட்டவா போய | C10: முனி
A11: 59 | B11: சேரா போய | C11: சேராமான் முனி
A12: 59 | B12: சேராபோய | C12: சேராமான் முனிக்கும்
A13: 65 | B13: தலை முக்கியா | C13: தலைவர், முக்கியஸ்தர் , தலை கட்டு
... A84: 403 | B84: அக்கா | C84: அக்கா , வளையல்
A85: 119;87;342;176 | B85: பாணி ரக்கானெக் > நீர் வைக்கபடுகிறது ; கி நிசானி > தெரிகிறது, இருக்கிறது, உண்மை | C85: இரட்டை மாட்டு ஏர் உழுது விவசாயம் அருமை
A86: 146;195;343;403;87;342;1 | B86: காற்று ஓடை ஆதி சக்தி மாதா முக்கியம் | C86: காற்று மத்து கடைய, மழைநீர் கால்வாயில் ஓட, நீர் குளம் குட்டை ஏரியில் நிரம்ப, அக்கமார்கள் நடந்து, நீர் குடம் எடுக்க, என்னே அந்நாள், கடவுள் கருணை
A87: 171;59;342;176 | B87: சீறி பேன் > முக்கியா; கி நிசானி > தெரிகிறது, இருக்கிறது, உண்மை | C87: கை உயர்த்தி பேசு பால் வளம் முனிகள் பராமரிப்பில் வந்தது
A88: 175;230;344;53;65;233;342 | B88: வேலச்சியாளின் புத்திரன் பகந்தி போது கோயா தலை முக்கிய கோருமேடு | C88: மூன்று உறி விளக்கு எண்ணெய் ஆதான் கோரு மேட்டு மலை தலை முண்டாசும் போத்து கோயா பகந்தியும் பகிர்ந்து கொண்டார்கள்
A89: 177;197;192;341;89;328 | B89: இந்த மூன்றும் அம்பாரத்தில் சபையில் நமது வளர்ச்சிக்கான அளவீடுகளாக வைக்க வேண்டும்: தங்கம், ஆடை, வீடு இவற்றின் நுட்பம் | C89: நம்முடைய புஷ்டி தாது சக்தியின் அளவீடு நம்மிடம் உள்ள மதிய மாளிகைகள், ஆடை ஆபரணம், தங்கம் உலோகம் என்ற மூன்று துறையின் வளர்ச்சி
A90: 183;169;99;387;59;182;293;342 | B90: பத்தோமாள் விளைநிலம் முக்கியம் அத்துடன் பத்து போத்து கால் முக்கியம் | C90: சேராமான் முனியிடம் பத்து பட்டி ஓமாளிகை பத்து நெல் போது பத்து போத்துகால் கரும்பு பயிர் இடப்பட்டுள்ளது
A91: 204;230;342 | B91: தானிய குவியல் உள்ளது | C91: தானிய குவியல்கள் மூட்டைகள் மாட்டு வண்டியில் அனுப்ப தயாராக உள்ளது
A92: 244;342 | B92: சபை கூட்டம் செல்கிறது | C92: கோயிலுக்கு நேர்ந்த மாடு , மாட்டு பட்டி, ஆயிரம் மாடு
A93: 29;336;99;104;162 | B93: இர்பில் அம்பாள் நுர்தோர் நாலோமால் [ இருவில் அம்பாள் கிராமத்தில் நல்ல புகழ் பெற்றவர்] | C93: இருவில் பெஉத்தி ருமாள் நூற்றில் ஒரு நல்ல பெருமாள் / இரட்டை மாட்டு செக்கு நல்லதோர் உத்தி
A94: 3;216;229;343;59;342 | B94: இங்கு கோயா பாரி பகந்தி குரு முக்கியா உள்ளார் | C94: அகோரி பகந்தி முத்தன்
A95: 336;89;211 | B95: கிராம முக்கியா / முதன்மை அதிகாரி | C95: மூன்று கானம் நிறுத்து ஒரு பணம் / ஒரு செக்கு கானம் நிறுத்து மூன்று பணம் / கானம் மூன்று நிறுத்து ஒரு பாலன் எடை
A96: 375;65;72;336;89;211 | B96: விளைநிலம் முக்கியம், தலை முக்கியம், சேரா பொய்யா தேவன் முக்கியம் என்பர் நூலார் | C96: நெல் பாதுகாப்பு அன்னம் பாதுகாப்பு, தலையாய சேரா ஆய - நூறு மூவாயிரம் நூலோர் பாதுகாப்பு
... A101: 86;102;15 | B101: இவர் முதன்மை பாதுகாவலர் | C101: வரும் முந் காப்போன் காவடியோன் முருகன் / மகமாயி மும்மாரி முத்துமாரி

Sheet Final_Tables_Kangali_Puru
B4: SNO | C4: KangaliRef | D4: Seal_Ref | E4: PositionFR | F4: IM_Ref_Pic/Ivfont/Kangali | G4: IM_Ref_No_RightToLeft | H4: Kangali | I4: Puru
B5: 1 | C5: P99/SN194/103 | D5: MD1531 | E5: 0 | G5: 171;59;342;176 | H5: சீறி பேன் > முக்கியா; கி நிசானி > தெரிகிறது, இருக்கிறது, உண்மை | I5: கை உயர்த்தி பேசு பால் வளம் முனிகள் பராமரிப்பில் வந்தது
D6: MD1532 | E6: 1 | F6:  | G6: 171 | H6: சீறி | I6: கை,ஐந்து, உயர்த்து, தீ பந்தம் , கொடி
D7: MD1532 | E7: 2 | F7:  | G7: 59 | H7: பெண், பேன் | I7: மீன், முனி, நீர் சிலந்தி,போர்த்திய ஆள் பெண், புழு, புலி
D8: MD1532 | E8: 3 | F8:  | G8: 342 | H8: ஆனா | I8: மாடு, பசு, ஆ, அண்டா , குளம், மரக்கால் , சால்
D9: MD1532 | E9: 4 | F9:  | G9: 176 | H9: கீரா | I9: ஐந்து, விரல்கள், கீறி,சீப்பு, அரிவாள்
B10: SNO | C10: KangaliRef | D10: Seal_Ref | E10: PositionFR | F10: IM_Ref_Pic/Ivfont/Kangali | G10: IM_Ref_No_RightToLeft | H10: Kangali | I10: Puru
B11: 2 | C11: P64/Sn4/HR1940-581 | D11: HP4444 | E11: 0 | G11: 119;87;342;176 | H11: பாணி ரக்கானெக் > நீர் வைக்கபடுகிறது ; கி நிசானி > தெரிகிறது, இருக்கிறது, உண்மை | I11: இரட்டை மாட்டு ஏர் உழுது விவசாயம் அருமை
D12: HP4444 | E12: 1 | F12:  | G12: 119 | H12: யேர் | I12: நீர், ஏர், உழவு, மழை, பன்னிரண்டு, எண்ணிக்கை, அடுக்கு
D13: HP4444 | E13: 2 | F13:  | G13: 87 | H13: இரு | I13: இரண்டு, ஈர்,
D14: HP4444 | E14: 3 | F14:  | G14: 342 | H14: ஆனா | I14: மாடு, பசு, ஆ, அண்டா , குளம், மரக்கால் , சால்
D15: HP4444 | E15: 1 | F15:  | G15: 176 | H15: கீரா | I15: ஐந்து, விரல்கள், கீறி,சீப்பு, அரிவாள்
B16: SNO | C16: KangaliRef | D16: Seal_Ref | E16: PositionFR | F16: IM_Ref_Pic/Ivfont/Kangali | G16: IM_Ref_No_RightToLeft | H16: Kangali | I16: Puru
B17: 3 | C17: P62/Sn8/HR1940-372 | D17: HP4372 | E17: 0 | G17: 48;136;193;342 | H17: பருத்தி பயிர், ஆடை நெய்து தயார் நிலையை காட்டுகிறது – இது வியாபாரி தம்மிடம் இருப்பதை தெரிவிக்கிறது | I17: செல்வம் நிறைந்த பகுதி என்றும் காடு மலை சார்ந்த பகுதி என்ற குறிப்பு
D18: HP4372 | E18: 1 | F18:  | G18: 48 | H18: பருத்தி | I18: மலை தேன், மலர்,
D19: HP4372 | E19: 2 | F19:  | G19: 136 | H19: கோபுரம் குவியல் அம்பாரம் | I19: குடிசை, வீடு, கோபுரம், குவியல்
D20: HP4372 | E20: 3 | G20: 193 | H20: துணி ஆடை | I20: தொப்பி,
D21: HP4372 | E21: 4 | F21:  | G21: 342 | H21: ஆனா | I21: மாடு, பசு, ஆ, அண்டா , குளம், மரக்கால் , சால்
D22: HP4372 | E22: 5 | F22:  | G22: 176 | H22: கீரா | I22: ஐந்து, விரல்கள், கீறி,சீப்பு, அரிவாள்
D23: HP4372 | E23: 6 | F23:  | G23: 176 | H23: கீரா | I23: ஐந்து, விரல்கள், கீறி,சீப்பு, அரிவாள்
B24: SNO | C24: KangaliRef | D24: Seal_Ref | E24: PositionFR | F24: IM_Ref_Pic/Ivfont/Kangali | G24: IM_Ref_No_RightToLeft | H24: Kangali | I24: Puru
B25: 4 | C25: P100/SN200/1536 | D25: MD1536 | E25: 0 | G25: 146;195;343;403;87;342;1 | H25: காற்று ஓடை ஆதி சக்தி மாதா முக்கியம் | I25: காற்று மத்து கடைய, மழைநீர் கால்வாயில் ஓட, நீர் குளம் குட்டை ஏரியில் நிரம்ப, அக்கமார்கள் நடந்து, நீர் குடம் எடுக்க, என்னே அந்நாள், கடவுள் கருணை
D26: MD1536 | E26: 1 | G26: 146 | H26: மாட்டாயா | I26: காற்று மத்து
D27: MD1536 | E27: 2 | F27:  | G27: 195 | H27: கால்வாள் | I27: ஓடை , வாய்க்கால்
D28: MD1536 | E28: 3 | G28: 343 | H28: ஆந்தி | I28: குளம், குட்டை
D29: MD1536 | E29: 4 | G29: 403 | H29: அக்கா | I29: அக்கா , வளையல்
D30: MD1536 | E30: 5 | F30:  | G30: 87 | H30: இரு | I30: இரு, நடந்து, இரண்டு
D31: MD1536 | E31: 6 | G31: 342 | H31: ஆனா | I31: நீர் குடம்
D32: MD1536 | E32: 7 | F32:  | G32: 1 | H32: ஆள் | I32: கடவுள், அந்நாள்
B33: SNO | C33: KangaliRef | D33: Seal_Ref | E33: PositionFR | F33: IM_Ref_Pic/Ivfont/Kangali | G33: IM_Ref_No_RightToLeft | H33: Kangali | I33: Puru
B34: 5 | C34: P97/Sn187/1420 | D34: MD1420 | E34: 0 | G34: 175;230;344;53;65;233;342 | H34: வேலச்சியாளின் புத்திரன் பகந்தி போது கோயா தலை முக்கிய கோருமேடு | I34: மூன்று உறி விளக்கு எண்ணெய் ஆதான் கோரு மேட்டு மலை தலை முண்டாசும் போத்து கோயா பகந்தியும் பகிர்ந்து கொண்டார்கள்
D35: MD1420 | E35: 1 | F35:  | G35: 175 | H35: வேலச்சியாள் | I35: ஆமணக்கு விதை, உறி, வேலு ஆச்சியாள்
D36: MD1420 | E36: 2 | F36:  | G36: 230 | H36: முறி | I36: முறி, உடைத்தால், எடுத்தல் , அரைத்தல், மூவர்
D37: MD1420 | E37: 3 | F37:  | G37: 344 | H37: பகந்தி | I37: பகந்தி முனிவர், விஷ்ணு, நாமம்
D38: MD1420 | E38: 4 | F38:  | G38: 53 | H38: போத்து கோயா | I38: போத்து கோயா கரும்பு விளைச்சல் சமுதாயம்
D39: MD1420 | E39: 5 | F39:  | G39: 65 | H39: தலை முக்கியா | I39: தலைவர், முக்கியஸ்தர் , தலை கட்டு
D40: MD1420 | E40: 6 | G40: 233 | H40: கோரு மேட்டா | I40: மலை கிராமங்கள் , வீடுகள், கூட்டம்
E41: 7 | F41:  | G41: 342 | H41: ஆந்த | I41: அளவீடு, மரக்கால், மாடுகள் , வழக்கம், முறை
B42: SNO | C42: KangaliRef | D42: Seal_Ref | E42: PositionFR | F42: IM_Ref_Pic/Ivfont/Kangali | G42: IM_Ref_No_RightToLeft | H42: Kangali | I42: Puru
B43: 6 | C43: P86/SN134/2587 | D43: MD2587 | E43: 0 | G43: 86;102;15 | H43: இவர் முதன்மை பாதுகாவலர் | I43: வரும் முந் காப்போன் காவடியோன் முருகன் / மகமாயி மும்மாரி முத்துமாரி
D44: MD2587 | E44: 1 | F44:  | G44: 86 | H44: ஒரு | I44: ஒன்று, கோல், காவல், மழை
D45: MD2587 | E45: 2 | F45:  | G45: 102 | H45: மூன் | I45: மூன்று, முப்போகம், மும்மாரி
D46: MD2587 | E46: 3 | F46:  | G46: 15 | H46: காவடியாள் ஆந்த | I46: காவடி, பால் காரர், தீவனம் அளிப்பவர் , மாட்டு பட்டி காவலர்
B47: SNO | C47: KangaliRef | D47: Seal_Ref | E47: PositionFR | F47: IM_Ref_Pic/Ivfont/Kangali | G47: IM_Ref_No_RightToLeft | H47: Kangali | I47: Puru
B48: 7 | C48: P76/SN82/2110 | D48: MD2507 | E48: 0 | G48: 375;65;72;336;89;211 | H48: விளைநிலம் முக்கியம், தலை முக்கியம், சேரா பொய்யா தேவன் முக்கியம் என்பர் நூலார் | I48: நெல் பாதுகாப்பு அன்னம் பாதுகாப்பு, தலையாய சேரா ஆய - நூறு மூவாயிரம் நூலோர் பாதுகாப்பு
D49: MD2507 | E49: 1 | G49: 375 | H49: நெல் பாது | I49: நெல் விதை
D50: MD2507 | E50: 2 | F50:  | G50: 65 | H50: தலாபோய் | I50: தலை முன் நிற்பவர்
D51: MD2507 | E51: 3 | F51:  | G51: 72 | H51: சேராபோய் | I51: சேரன் முன் நிற்பவர்
D52: MD2507 | E52: 4 | G52: 336 | H52: நுர் | I52: நூர் , நூறாயிரம் , நெல் அரைத்தல்
D53: MD2507 | E53: 5 | F53:  | G53: 89 | H53: மூன் | I53: மூவாயிரம்
D54: MD2507 | E54: 6 | F54:  | G54: 211 | H54: நூல், ஆர் | I54: உறுதி பயன் நூலோர் , நிலை நிறுத்து
B55: SNO | C55: KangaliRef | D55: Seal_Ref | E55: PositionFR | F55: IM_Ref_Pic/Ivfont/Kangali | G55: IM_Ref_No_RightToLeft | H55: Kangali | I55: Puru
B56: 8 | C56: P61/SN3/MD1937-420 | D56: MD2420 | E56: 0 | G56: 3;216;229;343;59;342 | H56: இங்கு கோயா பாரி பகந்தி குரு முக்கியா உள்ளார் | I56: அகோரி பகந்தி முத்தன்
D57: MD2420 | E57: 1 | F57:  | G57: 3 | H57: ஆள் | I57: ஆள்
D58: MD2420 | E58: 2 | F58:  | G58: 216 | H58: கோயா | I58: கோயா சின்னம்
D59: MD2420 | E59: 3 | G59: 229 | H59: பாரி | I59: பாரி சின்னம்
D60: MD2420 | E60: 4 | F60:  | G60: 343 | H60: பகந்தி | I60: பகந்தி முனிவர், விஷ்ணு, நாமம்
D61: MD2420 | E61: 5 | F61:  | G61: 59 | H61: முட்டவா போய | I61: முனிவர், முதலாம் குரு
D62: MD2420 | E62: 6 | F62:  | G62: 342 | H62: ஆந்த | I62: ஆம், அம், ஆ , அண்டா, குண்டா, மரக்கால், அளவு, மாடு, பசு
B63: SNO | C63: KangaliRef | D63: Seal_Ref | E63: PositionFR | F63: IM_Ref_Pic/Ivfont/Kangali | G63: IM_Ref_No_RightToLeft | H63: Kangali | I63: Puru
B64: 9 | C64: P60/SN1/MD1937-49 | D64: WA9811 | E64: 0 | G64: 29;336;99;104;162 | H64: இர்பில் அம்பாள் நுர்தோர் நாலோமால் [ இருவில் அம்பாள் கிராமத்தில் நல்ல புகழ் பெற்றவர்] | I64: இருவில் பெஉத்தி ருமாள் நூற்றில் ஒரு நல்ல பெருமாள் / இரட்டை மாட்டு செக்கு நல்லதோர் உத்தி
D65: WA9811 | E65: 1 | G65: 29 | H65: இர்பில் அம்பாள் | I65: இரட்டை மாடு பூட்டிய
D66: WA9811 | E66: 2 | G66: 336 | H66: நூர் | I66: செக்கு நூர் நொறுக்கு
D67: WA9811 | E67: 3 | F67:  | G67: 99 | H67: தோர் | I67: வோர்
D68: WA9811 | E68: 4 | F68:  | G68: 104 | H68: நால் | I68: நல்ல
D69: WA9811 | E69: 5 | G69: 162 | H69: ஓமால் | I69: மகசூல், நெல், ஈட்டியது
B70: SNO | C70: KangaliRef | D70: Seal_Ref | E70: PositionFR | F70: IM_Ref_Pic/Ivfont/Kangali | G70: IM_Ref_No_RightToLeft | H70: Kangali | I70: Puru
B71: 10 | C71: P60/SN2/MD1937-524 | D71: MD2015 | E71: 0 | G71: 336;89;211 | H71: கிராம முக்கியா / முதன்மை அதிகாரி | I71: மூன்று கானம் நிறுத்து ஒரு பணம் / ஒரு செக்கு கானம் நிறுத்து மூன்று பணம் / கானம் மூன்று நிறுத்து ஒரு பாலன் எடை
D72: MD2015 | E72: 1 | G72: 336 | H72: நூர் | I72: செக்கு, நொறுக்கு, சட்டியும் அகப்பையும், செக்கு கானம்
D73: MD2015 | E73: 2 | F73:  | G73: 89 | H73: மூன் | I73: மூன்று, வேலி
D74: MD2015 | E74: 3 | F74:  | G74: 211 | H74: சார்,ஆர் | I74: அம்பு, ஈட்டி, காவல், வேலன், முருகன், துலா முள்
B75: SNO | C75: KangaliRef | D75: Seal_Ref | E75: PositionFR | F75: IM_Ref_Pic/Ivfont/Kangali | G75: IM_Ref_No_RightToLeft | H75: Kangali | I75: Puru
B76: 11 | C76: P61/SN5/MD1937-669 | D76: MD2669 | E76: 0 | G76: 59;121;342 | H76: குரு முக்கியாவின் கருணை | I76: முனிகளால் பால் வளம் மிகுதி
D77: MD2669 | E77: 1 | F77:  | G77: 59 | H77: முட்டவா போய | I77: முனி
D78: MD2669 | E78: 2 | F78:  | G78: 121 | H78: பீர | I78: பீரிட, மிக, முழுமையான
D79: MD2669 | E79: 3 | F79:  | G79: 342 | H79: ஆந்த | I79: பால், பசு, மரக்கால்
B80: SNO | C80: KangaliRef | D80: Seal_Ref | E80: PositionFR | F80: IM_Ref_Pic/Ivfont/Kangali | G80: IM_Ref_No_RightToLeft | H80: Kangali | I80: Puru
B81: 12 | C81: P61/SN6/HR1940-344 | D81: HP4344 | E81: 0 | G81: 177;197;192;341;89;328 | H81: இந்த மூன்றும் அம்பாரத்தில் சபையில் நமது வளர்ச்சிக்கான அளவீடுகளாக வைக்க வேண்டும்: தங்கம், ஆடை, வீடு இவற்றின் நுட்பம் | I81: நம்முடைய புஷ்டி தாது சக்தியின் அளவீடு நம்மிடம் உள்ள மதிய மாளிகைகள், ஆடை ஆபரணம், தங்கம் உலோகம் என்ற மூன்று துறையின் வளர்ச்சி
D82: HP4344 | E82: 1 | F82:  | G82: 177 | H82: கோலா | I82: அளவு கோல்
D83: HP4344 | E83: 2 | F83:  | G83: 197 | H83: மாடா | I83: மாட மாளிகை வீடு
D84: HP4344 | E84: 3 | G84: 192 | H84: குடரதே | I84: ஆடை ஆபரணம்
D85: HP4344 | E85: 4 | G85: 341 | H85: கோவதா | I85: தங்கம், உலோக தொழில்
D86: HP4344 | E86: 5 | F86:  | G86: 89 | H86: மூந்த | I86: மூன்றும்
D87: HP4344 | E87: 6 | F87:  | G87: 328 | H87: ஆளாங்க | I87: அளவு
B88: SNO | C88: KangaliRef | D88: Seal_Ref | E88: PositionFR | F88: IM_Ref_Pic/Ivfont/Kangali | G88: IM_Ref_No_RightToLeft | H88: Kangali | I88: Puru
B89: 13 | C89: P62/SN12/MD1937-449 | D89: MD1561 | E89: 0 | G89: 204;230;342 | H89: தானிய குவியல் உள்ளது | I89: தானிய குவியல்கள் மூட்டைகள் மாட்டு வண்டியில் அனுப்ப தயாராக உள்ளது
D90: MD1561 | E90: 1 | F90:  | G90: 204 | H90: தூக்கா தூக்கல் குவியல் | I90: குவியல், கோபுரம்
D91: MD1561 | E91: 2 | F91:  | G91: 230 | H91: முறி மூன்று உறி தொகுப்பு | I91: மூட்டைகள் உறி நிறைய மூன்று நிறை
D92: MD1561 | E92: 3 | F92:  | G92: 342 | H92: ஆந்த அவை | I92: மாடு, பசு, ஆம், அம் , ஆ , ஆந்தை
B93: SNO | C93: KangaliRef | D93: Seal_Ref | E93: PositionFR | F93: IM_Ref_Pic/Ivfont/Kangali | G93: IM_Ref_No_RightToLeft | H93: Kangali | I93: Puru
B94: 14 | C94: P62/SN14/MD1940-502 | D94: MD1550 | E94: 0 | G94: 67;244;342 | H94: சபையில் முக்கிய பிரதான் தலைமை வகிக்கிறார் | I94: கோயில் முனிவர் மக்களுக்கு பாதுகாப்பு / முனி ஈஸ்வரர் கோயில் / முனி எசவரர் கோயிலுக்கு அளித்த பசு மாடு
D95: MD1550 | E95: 1 | F95:  | G95: 67 | H95: அதி முக்கிய முனி ஈஸ்வர் | I95: அதி முக்கிய முனி ஈஸ்வர்
D96: MD1550 | E96: 2 | G96: 244 | H96: சபை கோயில் | I96: சபை கோயில்
D97: MD1550 | E97: 3 | F97:  | G97: 342 | H97: உள்ளார், காட்சி அளிக்கிறார் | I97: உள்ளார், காட்சி அளிக்கிறார்
B98: SNO | C98: KangaliRef | D98: Seal_Ref | E98: PositionFR | F98: IM_Ref_Pic/Ivfont/Kangali | G98: IM_Ref_No_RightToLeft | H98: Kangali | I98: Puru
B99: 15 | C99: P62/SN16/- | D99: 974 | E99: 0 | G99: 244;342 | H99: சபை கூட்டம் செல்கிறது | I99: கோயிலுக்கு நேர்ந்த மாடு , மாட்டு பட்டி, ஆயிரம் மாடு
D100: 974 | E100: 1 | G100: 244 | H100: கோயில் | I100: கோயில், கட்டிடம்
D101: 974 | E101: 2 | F101:  | G101: 342 | H101: ஆந்த | I101: மாடு பசு
B102: SNO | C102: KangaliRef | D102: Seal_Ref | E102: PositionFR | F102: IM_Ref_Pic/Ivfont/Kangali | G102: IM_Ref_No_RightToLeft | H102: Kangali | I102: Puru
B103: 16 | C103: P75/SN76/MD-3023 | D103: MD3023 | E103: 0 | G103: 183;169;99;387;59;182;293;342 | H103: பத்தோமாள் விளைநிலம் முக்கியம் அத்துடன் பத்து போத்து கால் முக்கியம் | I103: சேராமான் முனியிடம் பத்து பட்டி ஓமாளிகை பத்து நெல் போது பத்து போத்துகால் கரும்பு பயிர் இடப்பட்டுள்ளது
...

Sheet Copilot_fed_initial_data
E2: Sno | F2: Description | G2: Position from Right | H2: Script Sign | I2: Script ID IM77 | K2: My initial obervation | L2: My initial remarks | M2: H1 — Royal Order to Merchants (Irungōvin āṇai | N2: H2 — Guild / Community Notice (Koya–Gondala association) | O2: H3 — Cultural/Poetic Direction (Nāṭu araca kōṭṭai) | P2: My revised view | V2: Position of sign from left | W2: L1 | X2: L2 | Y2: L3 | Z2: L4 | AA2: L5 | AB2: L6 | AC2: L7 | AD2: L8 | AE2: L9 | AF2: L10
E3: 1 | F3: L1 | G3: Wall_Sign_R10 | I3: 391 | M3: wheel/transport/authority marker — interpreted as 'transport' or 'public facility' | N3: community/wheel — community emblem (Gondola/Koya) | O3: symbolic motif used as ritual or festival marker | V3: Script Sign
E4: 2 | F4: L2 | G4: Wall_Sign_R9 | I4: 256 | M4: thread/rod/order — interpreted as 'order/command' (āṇai) | N4: thread/implement — tool for communal craft/registration | O4: token/implement — symbolic of invocation or announcement | V4: Script ID IM77 | W4: 391 | X4: 256 | Y4: 327 | Z4: 391 | AA4: 261 | AB4: 134 | AC4: 86 | AD4: 391 | AE4: 391 | AF4: 53
E5: 3 | F5: L3 | G5: Wall_Sign_R8 | I5: 327 | M5: leaf/king/royal marker — interpreted as 'king/capitan (arasa/arasan)' | N5: leaf/leader marker — local chieftain or guild head | O5: royal/poetic title marker — 'arasa/arasi' linking to patronage
E6: 4 | F6: L4 | G6: Wall_Sign_R7 | I6: 391 | M6: repeat as emphasis on communal/transport role | N6: repetition of community emblem | O6: festival/ceremonial motif
E7: 5 | F7: L5 | G7: Wall_Sign_R6 | I7: 261 | M7: diamond/well/fort — 'fort' (kōṭṭai) or 'well' (kiṇṟu) | N7: workplace/fortification — local production site or protected market | O7: site/fort — 'kōṭṭai' as royal palace
E8: 6 | F8: L6 | G8: Wall_Sign_R5 | I8: 134 | M8: head/hut — 'head of fort' / 'chief' (thalai) | N8: head/hut — local head's lodge | O8: head/authority — patron/chief
E9: 7 | F9: L7 | G9: Wall_Sign_R4 | I9: 86 | M9: stick/rod/one — 'leader/authority marker' (āri) | N9: staff/stake — marker for chief or custodian | O9: symbolic staff — ceremonial sign
E10: 8 | F10: L8 | G10: Wall_Sign_R3 | I10: 391 | M10: wheel/transport/merchant function | N10: community emblem (merchant/transport role) | O10: ritual motif
E11: 9 | F11: L9 | G11: Wall_Sign_R2 | I11: 391 | M11: wheel/transport/merchant function | N11: community emblem | O11: ritual motif
E12: 10 | F12: L10 | G12: Wall_Sign_R1 | I12: 53 | M12: cart/paired-bullock — 'transport/merchants' or 'irattai mādu' (double bullock) | N12: potukoyal / cart — reference to community or occupational group | O12: instrument/cart — possibly indicating gifts or transport of patronage goods
F13: Sno
S14: IM77 ID | T14: Interpretation / gloss
G15: Position from Right | H15: Script Sign | I15: Script ID IM77 | K15: Position from Right | L15: signs_vari | M15: Sign No | N15: Signs | S15: 391 | T15: symbolic motif used as ritual or festival marker
G16: Seal_M314_R1 | I16: 391 | K16: Seal_M314_R1 | M16: M391 | S16: 256 | T16: token/implement — symbolic of invocation or announcement
G17: Seal_M314_R2 | I17: 99 | K17: Seal_M314_R2 | M17: M99 | S17: 327 | T17: royal/poetic title marker — 'arasa/arasi' linking to patronage
G18: Seal_M314_R3 | I18: 65 | K18: Seal_M314_R3 | M18: M65 | S18: 391 | T18: festival/ceremonial motif
G19: Seal_M314_R4 | I19: 67 | K19: Seal_M314_R4 | M19: M67 | S19: 261 | T19: site/fort — 'kōṭṭai' as royal palace
G20: Seal_M314_R5 | I20: 59 | K20: Seal_M314_R5 | M20: M59 | S20: 134 | T20: head/authority — patron/chief
G21: Seal_M314_R6 | I21: 211 | K21: Seal_M314_R6 | M21: M211 | S21: 86 | T21: symbolic staff — ceremonial sign
G22: Seal_M314_R7 | I22: 105 | K22: Seal_M314_R7 | M22: M105 | S22: 391 | T22: ritual motif
G23: Seal_M314_R8 | I23: 129 | K23: Seal_M314_R8 | M23: M129 | S23: 391 | T23: ritual motif
G24: Seal_M314_R9 | I24: 129 | K24: Seal_M314_R9 | M24: M129 | S24: 53 | T24: instrument/cart — possibly indicating gifts or transport of patronage goods
G25: Seal_M314_R10 | I25: 336 | K25: Seal_M314_R10 | M25: M336
G26: Seal_M314_R11 | I26: 347 | K26: Seal_M314_R11 | M26: M347
G27: Seal_M314_R12 | I27: 342 | K27: Seal_M314_R12 | M27: M342
G28: Seal_M314_R13 | I28: 89 | K28: Seal_M314_R13 | M28: M89
G29: Seal_M314_R14 | I29: 381 | K29: Seal_M314_R14 | M29: M381
G30: Seal_M314_R15 | I30: 180 | K30: Seal_M314_R15 | M30: M180
G31: Seal_M314_R16 | I31: 307 | K31: Seal_M314_R16 | M31: M307
G32: Seal_M314_R17 | I32: 1 | K32: Seal_M314_R17 | M32: M1
G33: Seal_M314_R18 | I33: 1361 | K33: Seal_M314_R18 | M33: M1361
G34: Seal_M314_R19 | I34: 1022 | K34: Seal_M314_R19 | M34: M1022
G35: Seal_M314_R20 | I35: 1400 | K35: Seal_M314_R20 | M35: M1400
F38: Sno | G38: Position from Right | H38: Script Sign | I38: Script ID IM77
F39: 1 | G39: Wall_Sign_R10 | I39: 391
F40: 2 | G40: Wall_Sign_R9 | I40: 256 | L40: Script IB IM77 | M40: Frequncy, given case | N40: Script IB IM77 | O40: Frequncy, given case
F41: 3 | G41: Wall_Sign_R8 | I41: 327 | L41: 1 | M41: 1 | N41: 391 | O41: 5
F42: 4 | G42: Wall_Sign_R7 | I42: 391 | L42: 53 | M42: 1 | N42: 129 | O42: 2
F43: 5 | G43: Wall_Sign_R6 | I43: 261 | L43: 59 | M43: 1 | N43: 1400 | O43: 1
F44: 6 | G44: Wall_Sign_R5 | I44: 134 | L44: 65 | M44: 1 | N44: 1361 | O44: 1
F45: 7 | G45: Wall_Sign_R4 | I45: 86 | L45: 67 | M45: 1 | N45: 1022 | O45: 1
F46: 8 | G46: Wall_Sign_R3 | I46: 391 | L46: 86 | M46: 1 | N46: 381 | O46: 1
F47: 9 | G47: Wall_Sign_R2 | I47: 391 | L47: 89 | M47: 1 | N47: 347 | O47: 1
F48: 10 | G48: Wall_Sign_R1 | I48: 53 | L48: 99 | M48: 1 | N48: 342 | O48: 1
F49: 11 | G49: Seal_M314_R1 | I49: 391 | L49: 105 | M49: 1 | N49: 336 | O49: 1
F50: 12 | G50: Seal_M314_R2 | I50: 99 | L50: 129 | M50: 2 | N50: 327 | O50: 1
F51: 13 | G51: Seal_M314_R3 | I51: 65 | L51: 134 | M51: 1 | N51: 307 | O51: 1
F52: 14 | G52: Seal_M314_R4 | I52: 67 | L52: 180 | M52: 1 | N52: 261 | O52: 1
... F65: 27 | G65: Seal_M314_R17 | I65: 1 | L65: 1400 | M65: 1 | N65: 1 | O65: 1
F66: 28 | G66: Seal_M314_R18 | I66: 1361 | L66: Grand Total | M66: 30
F67: 29 | G67: Seal_M314_R19 | I67: 1022
F68: 30 | G68: Seal_M314_R20 | I68: 1400

Sheet MD1531
C6: MD1531TableStarting | F6:  | G6:  | H6:  | I6:  | J6:  | K6: 
D7: Scholars | E7: IM77 concordance | F7: Single04 | G7: Single03 | H7: Single02 | I7: Single01 | J7: pair02 | K7: pair01
D8: signs in MD1531 | E8: L<176, 342, 59, 171>R | F8: 176 | G8: 342 | H8: 59 | I8: 171 | J8: 176342 | K8: 59171
D9: Kangali | E9: =_xlfn.CONCAT("[",I9,"]+","[",H9,"]+","[",G9,"]+","[",F9,"]"," >> சீறி பேன் கி நிசானி >> முக்கியா இருக்கிறார்") -> [சீறி]+[பெண், பேன் ]+[ஆனா ]+[கீரா] >> சீறி பேன் கி நிசானி >> முக்கியா இருக்கிறார் | F9: கீரா | G9: ஆனா | H9: பெண், பேன் | I9: சீறி | J9: கி நிசானி > தெரிகிறது, இருக்கிறது, உண்மை | K9: சீறி பேன் > முக்கியா | L9: =_xlfn.CONCAT(K9,J9) -> சீறி பேன் > முக்கியா கி நிசானி > தெரிகிறது, இருக்கிறது, உண்மை
D10: Yajna Devam | E10: =_xlfn.CONCAT("[",I10,"]+","[",H10,"]+","[",G10,"]+","[",F10,"]") -> [இ ]+[அன்,அம் ]+[ம ]+[த,த்த,ட ,ட்ட ] | F10: த,த்த,ட ,ட்ட | G10: ம | H10: அன்,அம் | I10: இ | J10: =_xlfn.CONCAT("[",G10,"]+","[",F10,"]") -> [ம ]+[த,த்த,ட ,ட்ட ] | K10: =_xlfn.CONCAT("[",I10,"]+","[",H10,"]") -> [இ ]+[அன்,அம் ]
D11: Mathivanan | E11: =_xlfn.CONCAT("[",I11,"]+","[",H11,"]+","[",G11,"]+","[",F11,"]") -> [இ ]+[கா]+[சா]+[??] | F11: ?? | G11: சா | H11: கா | I11: இ | J11: =_xlfn.CONCAT("[",G11,"]+","[",F11,"]") -> [சா]+[??] | K11: =_xlfn.CONCAT("[",I11,"]+","[",H11,"]") -> [இ ]+[கா]
D12: Mathiazagan | E12: =_xlfn.CONCAT("[",I12,"]+","[",H12,"]+","[",G12,"]+","[",F12,"]") -> [கை ]+[ன்,அன் ]+[ப , பு, பா ]+[கழி,களி,கணி ] | F12: கழி,களி,கணி | G12: ப , பு, பா | H12: ன்,அன் | I12: கை | J12: =_xlfn.CONCAT("[",G12,"]+","[",F12,"]") -> [ப , பு, பா ]+[கழி,களி,கணி ] | K12: =_xlfn.CONCAT("[",I12,"]+","[",H12,"]") -> [கை ]+[ன்,அன் ]
D13: Gurumurthy | E13: =_xlfn.CONCAT("[",I13,"]+","[",H13,"]+","[",G13,"]+","[",F13,"]") -> [தூக்கும் மனிதன்]+[மீன்]+[மீன் மண்டை ]+[ஐந்து] | F13: ஐந்து | G13: மீன் மண்டை | H13: மீன் | I13: தூக்கும் மனிதன் | J13: =_xlfn.CONCAT("[",G13,"]+","[",F13,"]") -> [மீன் மண்டை ]+[ஐந்து] | K13: =_xlfn.CONCAT("[",I13,"]+","[",H13,"]") -> [தூக்கும் மனிதன்]+[மீன்]
D14: purushothaman | E14: =_xlfn.CONCAT("[",I14,"]+","[",H14,"]+","[",G14,"]+","[",F14,"]") -> [கை,ஐந்து, உயர்த்து, தீ பந்தம் , கொடி ]+[மீன், முனி, நீர் சிலந்தி,போர்த்திய ஆள் பெண், புழு, புலி ]+[மாடு, பசு, ஆ, அண்டா , குளம், மரக்கால் , சால் ]+[ஐந்து, விரல்கள், கீறி,சீப்பு, அரிவாள் ] | F14: ஐந்து, விரல்கள், கீறி,சீப்பு, அரிவாள் | G14: மாடு, பசு, ஆ, அண்டா , குளம், மரக்கால் , சால் | H14: மீன், முனி, நீர் சிலந்தி,போர்த்திய ஆள் பெண், புழு, புலி | I14: கை,ஐந்து, உயர்த்து, தீ பந்தம் , கொடி | J14: =_xlfn.CONCAT("[",G14,"]+","[",F14,"]") -> [மாடு, பசு, ஆ, அண்டா , குளம், மரக்கால் , சால் ]+[ஐந்து, விரல்கள், கீறி,சீப்பு, அரிவாள் ] | K14: =_xlfn.CONCAT("[",I14,"]+","[",H14,"]") -> [கை,ஐந்து, உயர்த்து, தீ பந்தம் , கொடி ]+[மீன், முனி, நீர் சிலந்தி,போர்த்திய ஆள் பெண், புழு, புலி ]
C17: MD1531TableNext | F17:  | G17:  | H17:  | I17:  | J17:  | K17: 
D18: Scholars | E18: IM77 concordance | F18: Single04 | G18: Single03 | H18: Single02 | I18: Single01 | J18: pair02 | K18: pair01
D19: signs in MD1531 | E19: L<176, 342, 59, 171>R | F19: 176 | G19: 342 | H19: 59 | I19: 171 | J19: 176342 | K19: 59171
D20: பட எழுத்து காட்சி (seeing as picture) | E20: உயர்த்தி பேசு முனிகள் மாடுகளுக்கு தீவனம் அளிப்பது (praise feeding cattle by care takers) | F20: கீறி, ஐந்து, விரல், புல் | G20: பசு, மாடு, அண்டா, சால் | H20: முனி, பெண் , மீன் | I20: தீவட்டி, கை விரல் ஐந்து, உயர்த்து | J20: =_xlfn.CONCAT("[",F20,"]+","[",E20,"]") -> [கீறி, ஐந்து, விரல், புல் ]+[உயர்த்தி பேசு முனிகள் மாடுகளுக்கு தீவனம் அளிப்பது (praise feeding cattle by care takers)] | K20: =_xlfn.CONCAT("[",H20,"]+","[",I20,"]") -> [முனி, பெண் , மீன் ]+[தீவட்டி, கை விரல் ஐந்து, உயர்த்து ]
D21: நாம் கருதும் அகர வரிசை (proposed alphbets) | E21: உ+மா+ஆ +கை | F21: ப, பு, ல, நெ, வ | G21: ப, அ, மா | H21: மு, மீ | I21: கை, ஐ | J21: =_xlfn.CONCAT("[",G21,"]+","[",F21,"]") -> [ப, அ, மா ]+[ப, பு, ல, நெ, வ ] | K21: =_xlfn.CONCAT("[",I21,"]+","[",H21,"]") -> [கை, ஐ ]+[மு, மீ ]
D22: அசை (syllabic) | E22: உண் , மா , ஆ , கை | F22: புல், விரல் | G22: மா, ஆ | H22: முன், முனி | I22: உண் | J22: =_xlfn.CONCAT("[",G22,"]+","[",F22,"]") -> [மா, ஆ ]+[புல், விரல் ] | K22: =_xlfn.CONCAT("[",I22,"]+","[",H22,"]") -> [உண் ]+[முன், முனி ]
D23: சொற்கள் (word) | E23: உண்ண, முனி, மா, ஆ , கை | F23: புல், கீறி, வயல், நெல் | G23: மாடு, பசு | H23: முன்ன, முனிவர், முதல், பெண் | I23: உண்ண, உயர்த்த, ஏற்றம் | J23: =_xlfn.CONCAT("[",G23,"]+","[",F23,"]") -> [மாடு, பசு ]+[புல், கீறி, வயல், நெல் ] | K23: =_xlfn.CONCAT("[",I23,"]+","[",H23,"]") -> [உண்ண, உயர்த்த, ஏற்றம் ]+[முன்ன, முனிவர், முதல், பெண் ]
D24: வளரும் தொகுப்பு (growing collections ietrative as i+1th ) | E24: =_xlfn.TEXTJOIN(":",TRUE,D9:E14) -> Kangali:[சீறி]+[பெண், பேன் ]+[ஆனா ]+[கீரா] >> சீறி பேன் கி நிசானி >> முக்கியா இருக்கிறார்:Yajna Devam :[இ ]+[அன்,அம் ]+[ம ]+[த,த்த,ட ,ட்ட ]:Mathivanan:[இ ]+[கா]+[சா]+[??]:Mathiazagan:[கை ]+[ன்,அன் ]+[ப , பு, பா ]+[கழி,களி,கணி ]:Gurumurthy:[தூக்கும் மனிதன்]+[மீன்]+[மீன் மண்டை ]+[ஐந்து]:purushothaman :[கை,ஐந்து, உயர்த்து, தீ பந்தம் , கொடி ]+[மீன், முனி, நீர் சிலந்தி,போர்த்திய ஆள் பெண், புழு, புலி ]+[மாடு, பசு, ஆ, அண்டா , குளம், மரக்கால் , சால் ]+[ஐந்து, விரல்கள், கீறி,சீப்பு, அரிவாள் ]
E25: =_xlfn.TEXTJOIN(":",TRUE,D20:E23) -> பட எழுத்து காட்சி (seeing as picture):உயர்த்தி பேசு முனிகள் மாடுகளுக்கு தீவனம் அளிப்பது (praise feeding cattle by care takers):நாம் கருதும் அகர வரிசை (proposed alphbets):உ+மா+ஆ +கை :அசை (syllabic):உண் , மா , ஆ , கை :சொற்கள் (word):உண்ண, முனி, மா, ஆ , கை
C28: MD1531exploration
D29: signs in MD1531 | E29: L<176, 342, 59, 171>R
D30: வளரும் தொகுப்பு (growing collections ietrative as i+1th ) | E30: Kangali:[சீறி]+[பெண், பேன் ]+[ஆனா ]+[கீரா] >> சீறி பேன் கி நிசானி >> முக்கியா இருக்கிறார்:Yajna Devam :[இ ]+[அன்,அம் ]+[ம ]+[த,த்த,ட ,ட்ட ]:Mathivanan:[இ ]+[கா]+[சா]+[??]:Mathiazagan:[கை ]+[ன்,அன் ]+[ப , பு, பா ]+[கழி,களி,கணி ]:Gurumurthy:[தூக்கும் மனிதன்]+[மீன்]+[மீன் மண்டை ]+[ஐந்து]:purushothaman :[கை,ஐந்து, உயர்த்து, தீ பந்தம் , கொடி ]+[மீன், முனி, நீர் சிலந்தி,போர்த்திய ஆள் பெண், புழு, புலி ]+[மாடு, பசு, ஆ, அண்டா , குளம், மரக்கால் , சால் ]+[ஐந்து, விரல்கள், கீறி,சீப்பு, அரிவாள் ]
D31: தொல்காப்பியரின் ஒத்த காட்சிகள் -1 | E31: பட எழுத்து காட்சி (seeing as picture): உயர்த்தி பேசு முனிகள் மாடுகளுக்கு தீவனம் அளிப்பது (praise feeding cattle by care takers) நாம் கருதும் அகர வரிசை (proposed alphbets):உ+மா+ஆ +கை u+ma+aa :அசை (syllabic):உண் , மா , ஆ , கை un, maa,aa,kai:சொற்கள் (word):உண்ண, முனி, மா, ஆ , கை to eat,priest, saint, cow, hand
D32: தொல்காப்பியரின் ஒத்த காட்சிகள் -2 | E32: Refer to M C Kangali – Deciphering Indus Scripts through Gondi, page-99, SN0-194, given the seal that he refers as 103. This corresponds to IM77 – MD-1531 seal with scripts read from Right as 176,342,59 and 171. We start from Kangali’s reading the seal siri pen ki Nishan; he initially assigns Gondi words 171>siri; 59>pen; 342>aana; 176>kora. Same note in English is given in Tamil as, “ 171>சீறி; 59>பெண்; 342>ஆனா; 171>கீரா கோரா” But, look at the above, try to see intuitively and through various possible meanings in Tamil As given below as four different meanings சீறும் பெண் (பேன்) முனி ஆனா (கீரா) கோரா (the cow is uncontrollable) நம்மிடம் சீரிய பெண் மாடு பசு ஐந்து இருக்கிறது (we have five good quality cows) சீரிய முறையில் பேணிய ஐந்து பசு மாடுகள் உள்ளன (we have well trained five cows) கூறு ஐந்து பசு மந்தைகள் உள்ளன மேய்ப்பரோடு (tell that we have five lots of cow & cattles). Further, based on above approach, syllabic interpretation is also made as given below: எழுத்து கூட்டி: சிப்பாய் பசு ஐந்து (high quality cow, five) சீர்களாக: மாடு மேய்ப்பவர் >> [ஆயர்], [பெண்] ( herders, we get in Tamil syllable as aaayar pen > herder community ladies) பசு மாடு மந்தை ஐந்து >> [ஆய் >> ஆயர்], [ ஐ, ஐயன், ஐவர் ] ( cattle lot five and in Tamil we get the syllables iyan as respected) Note, we have selected the seal (IM77 – MD-1531 seal) because it contained our focus script IM77-342, here it appears in the middle, that is third from right. The above pairing help us to understand how it would affect the meaning in the seal positioning differently.
D33: எழுத்து கூட்டி / புது சொற்கள் syllabic alphabetic writing | E33: தமிழீ -Tamilii; தம்பி - brother

Sheet HP4444
C6: HP4444TableStarting | F6:  | G6:  | H6:  | I6:  | J6:  | K6: 
D7: Scholars | E7: IM77 concordance | F7: Single04 | G7: Single03 | H7: Single02 | I7: Single01 | J7: pair02 | K7: pair01
D8: signs in HP4444 | E8: L<176, 342, 87,1273>R | F8: 176 | G8: 342 | H8: 87 | I8: 1273 | J8: 176342 | K8: 87;1273
D9: Kangali | E9: =_xlfn.CONCAT("[",I9,"]+","[",H9,"]+","[",G9,"]+","[",F9,"]"," >> பாணி ரக்கானெக் கி நிசானி >> நீர் பிடிக்கப்படுகிறது வைக்கப்பட்டுள்ளது ") -> [யேர்]+[இரு ]+[ஆனா ]+[கீரா] >> பாணி ரக்கானெக் கி நிசானி >> நீர் பிடிக்கப்படுகிறது வைக்கப்பட்டுள்ளது | F9: கீரா | G9: ஆனா | H9: இரு | I9: யேர் | J9: கி நிசானி > தெரிகிறது, இருக்கிறது, உண்மை | K9: பாணி ரக்கானெக் > நீர் வைக்கபடுகிறது
D10: Yajna Devam | E10: =_xlfn.CONCAT("[",I10,"]+","[",H10,"]+","[",G10,"]+","[",F10,"]") -> [ஜ ]+[சோ ]+[ம ]+[த,த்த,ட ,ட்ட ] | F10: த,த்த,ட ,ட்ட | G10: ம | H10: சோ | I10: ஜ | J10: =_xlfn.CONCAT("[",G10,"]+","[",F10,"]") -> [ம ]+[த,த்த,ட ,ட்ட ] | K10: =_xlfn.CONCAT("[",I10,"]+","[",H10,"]") -> [ஜ ]+[சோ ]
D11: Mathivanan | E11: =_xlfn.CONCAT("[",I11,"]+","[",H11,"]+","[",G11,"]+","[",F11,"]") -> [??]+[??]+[சா]+[??] | F11: ?? | G11: சா | H11: ?? | I11: ?? | J11: =_xlfn.CONCAT("[",G11,"]+","[",F11,"]") -> [சா]+[??] | K11: =_xlfn.CONCAT("[",I11,"]+","[",H11,"]") -> [??]+[??]
D12: Mathiazagan | E12: =_xlfn.CONCAT("[",I12,"]+","[",H12,"]+","[",G12,"]+","[",F12,"]") -> [பண், பன்னீர்]+[இ, இல், இன் ]+[ப , பு, பா ]+[கழி,களி,கணி ] | F12: கழி,களி,கணி | G12: ப , பு, பா | H12: இ, இல், இன் | I12: பண், பன்னீர் | J12: =_xlfn.CONCAT("[",G12,"]+","[",F12,"]") -> [ப , பு, பா ]+[கழி,களி,கணி ] | K12: =_xlfn.CONCAT("[",I12,"]+","[",H12,"]") -> [பண், பன்னீர்]+[இ, இல், இன் ]
D13: Gurumurthy | E13: =_xlfn.CONCAT("[",I13,"]+","[",H13,"]+","[",G13,"]+","[",F13,"]") -> [ஓடுவது ]+[இரண்டு]+[மீன் மண்டை ]+[ஐந்து] | F13: ஐந்து | G13: மீன் மண்டை | H13: இரண்டு | I13: ஓடுவது | J13: =_xlfn.CONCAT("[",G13,"]+","[",F13,"]") -> [மீன் மண்டை ]+[ஐந்து] | K13: =_xlfn.CONCAT("[",I13,"]+","[",H13,"]") -> [ஓடுவது ]+[இரண்டு]
D14: purushothaman | E14: =_xlfn.CONCAT("[",I14,"]+","[",H14,"]+","[",G14,"]+","[",F14,"]") -> [நீர், ஏர், உழவு, மழை, பன்னிரண்டு, எண்ணிக்கை, அடுக்கு ]+[இரண்டு, ஈர்,]+[மாடு, பசு, ஆ, அண்டா , குளம், மரக்கால் , சால் ]+[ஐந்து, விரல்கள், கீறி,சீப்பு, அரிவாள் ] | F14: ஐந்து, விரல்கள், கீறி,சீப்பு, அரிவாள் | G14: மாடு, பசு, ஆ, அண்டா , குளம், மரக்கால் , சால் | H14: இரண்டு, ஈர், | I14: நீர், ஏர், உழவு, மழை, பன்னிரண்டு, எண்ணிக்கை, அடுக்கு | J14: =_xlfn.CONCAT("[",G14,"]+","[",F14,"]") -> [மாடு, பசு, ஆ, அண்டா , குளம், மரக்கால் , சால் ]+[ஐந்து, விரல்கள், கீறி,சீப்பு, அரிவாள் ] | K14: =_xlfn.CONCAT("[",I14,"]+","[",H14,"]") -> [நீர், ஏர், உழவு, மழை, பன்னிரண்டு, எண்ணிக்கை, அடுக்கு ]+[இரண்டு, ஈர்,]
C17: HP4444TableNext | F17:  | G17:  | H17:  | I17:  | J17:  | K17: 
D18: Scholars | E18: IM77 concordance | F18: Single04 | G18: Single03 | H18: Single02 | I18: Single01 | J18: pair02 | K18: pair01
D19: signs in HP4444 | E19: L<176, 342, 87,1273>R | F19: 176 | G19: 342
D20: பட எழுத்து காட்சி (seeing as picture) | E20: உயர்த்தி பேசு முனிகள் மாடுகளுக்கு தீவனம் அளிப்பது (praise feeding cattle by care takers) | F20: கீறி, ஐந்து, விரல், புல் , வயல், நெல் | G20: பசு, மாடு, அண்டா, சால், பால், குடுவை | H20: இரண்டு, ஈர், கழி | I20: மழை, ஆறு, நீர், மேடு பள்ளம், அடுக்கு, எண் , உழவு, கீறல் | J20: =_xlfn.CONCAT("[",F20,"]+","[",E20,"]") -> [கீறி, ஐந்து, விரல், புல் , வயல், நெல் ]+[உயர்த்தி பேசு முனிகள் மாடுகளுக்கு தீவனம் அளிப்பது (praise feeding cattle by care takers)] | K20: =_xlfn.CONCAT("[",H20,"]+","[",I20,"]") -> [இரண்டு, ஈர், கழி ]+[மழை, ஆறு, நீர், மேடு பள்ளம், அடுக்கு, எண் , உழவு, கீறல் ]
D21: நாம் கருதும் அகர வரிசை (proposed alphbets) | E21: உ+மா+ஆ +கை | F21: ப, பு, ல, நெ, வ | G21: ப, அ, மா | H21: இ , ஈ , க | I21: ஏ, எ , அ, ஆ , உ , ம | J21: =_xlfn.CONCAT("[",G21,"]+","[",F21,"]") -> [ப, அ, மா ]+[ப, பு, ல, நெ, வ ] | K21: =_xlfn.CONCAT("[",I21,"]+","[",H21,"]") -> [ஏ, எ , அ, ஆ , உ , ம]+[இ , ஈ , க ]
D22: அசை (syllabic) | E22: உண் , மா , ஆ , கை | F22: புல், விரல் | G22: மா, ஆ | H22: இது, ஈ , ஈர் | I22: ஏர், உழு, எண் , நீர் | J22: =_xlfn.CONCAT("[",G22,"]+","[",F22,"]") -> [மா, ஆ ]+[புல், விரல் ] | K22: =_xlfn.CONCAT("[",I22,"]+","[",H22,"]") -> [ஏர், உழு, எண் , நீர் ]+[இது, ஈ , ஈர் ]
D23: சொற்கள் (word) | E23: உண்ண, முனி, மா, ஆ , கை | F23: புல், கீறி, வயல், நெல் | G23: மாடு, பசு | H23: இரு, இரண்டு, கழி, ஈர்க்கு | I23: மழை, ஆறு, நீர், மேடு பள்ளம், அடுக்கு, எண் , உழவு, கீறல் | J23: =_xlfn.CONCAT("[",G23,"]+","[",F23,"]") -> [மாடு, பசு ]+[புல், கீறி, வயல், நெல் ] | K23: =_xlfn.CONCAT("[",I23,"]+","[",H23,"]") -> [மழை, ஆறு, நீர், மேடு பள்ளம், அடுக்கு, எண் , உழவு, கீறல் ]+[இரு, இரண்டு, கழி, ஈர்க்கு ]
D24: வளரும் தொகுப்பு (growing collections ietrative as i+1th ) | E24: =_xlfn.TEXTJOIN(":",TRUE,D9:E14) -> Kangali:[யேர்]+[இரு ]+[ஆனா ]+[கீரா] >> பாணி ரக்கானெக் கி நிசானி >> நீர் பிடிக்கப்படுகிறது வைக்கப்பட்டுள்ளது :Yajna Devam :[ஜ ]+[சோ ]+[ம ]+[த,த்த,ட ,ட்ட ]:Mathivanan:[??]+[??]+[சா]+[??]:Mathiazagan:[பண், பன்னீர்]+[இ, இல், இன் ]+[ப , பு, பா ]+[கழி,களி,கணி ]:Gurumurthy:[ஓடுவது ]+[இரண்டு]+[மீன் மண்டை ]+[ஐந்து]:purushothaman :[நீர், ஏர், உழவு, மழை, பன்னிரண்டு, எண்ணிக்கை, அடுக்கு ]+[இரண்டு, ஈர்,]+[மாடு, பசு, ஆ, அண்டா , குளம், மரக்கால் , சால் ]+[ஐந்து, விரல்கள், கீறி,சீப்பு, அரிவாள் ]
E25: =_xlfn.TEXTJOIN(":",TRUE,D20:E23) -> பட எழுத்து காட்சி (seeing as picture):உயர்த்தி பேசு முனிகள் மாடுகளுக்கு தீவனம் அளிப்பது (praise feeding cattle by care takers):நாம் கருதும் அகர வரிசை (proposed alphbets):உ+மா+ஆ +கை :அசை (syllabic):உண் , மா , ஆ , கை :சொற்கள் (word):உண்ண, முனி, மா, ஆ , கை
C28: HP4444exploration
D29: signs in HP4444 | E29: L<176, 342, 87,1273>R
D30: வளரும் தொகுப்பு (growing collections ietrative as i+1th ) | E30: Kangali:[யேர்]+[இரு ]+[ஆனா ]+[கீரா] >> பாணி ரக்கானெக் கி நிசானி >> நீர் பிடிக்கப்படுகிறது வைக்கப்பட்டுள்ளது :Yajna Devam :[ஜ ]+[சோ ]+[ம ]+[த,த்த,ட ,ட்ட ]:Mathivanan:[??]+[??]+[சா]+[??]:Mathiazagan:[பண், பன்னீர்]+[இ, இல், இன் ]+[ப , பு, பா ]+[கழி,களி,கணி ]:Gurumurthy:[ஓடுவது ]+[இரண்டு]+[மீன் மண்டை ]+[ஐந்து]:purushothaman :[நீர், ஏர், உழவு, மழை, பன்னிரண்டு, எண்ணிக்கை, அடுக்கு ]+[இரண்டு, ஈர்,]+[மாடு, பசு, ஆ, அண்டா , குளம், மரக்கால் , சால் ]+[ஐந்து, விரல்கள், கீறி,சீப்பு, அரிவாள் ]
D31: தொல்காப்பியரின் ஒத்த காட்சிகள் -1 | E31: பட எழுத்து காட்சி (seeing as picture):உயர்த்தி பேசு முனிகள் மாடுகளுக்கு தீவனம் அளிப்பது (praise feeding cattle by care takers):நாம் கருதும் அகர வரிசை (proposed alphbets):உ+மா+ஆ +கை :அசை (syllabic):உண் , மா , ஆ , கை :சொற்கள் (word):உண்ண, முனி, மா, ஆ , கை
D32: தொல்காப்பியரின் ஒத்த காட்சிகள் -2 | E32: ஏர் இரு மாடுகள் பூட்டி உழ அற்புதம் >> praise ploughing technology invented by the saint; ஆற்று நீர் பிடிப்பு பாசனம் விவசாயம் சிறப்பு
D33: எழுத்து கூட்டி / புது சொற்கள் syllabic alphabetic writing | E33: எகிறின - jumping ; ஆகிய - those, ஆகியே - became
